<CUBForeCast_New xmlns="http://Visy.Middleware.LGX.CUB.Schemas.CUBForeCastXML_New">
  <Header>
    <FieldA>Material No.</FieldA>
    <FieldB>Material Name</FieldB>
    <FieldC>UOM</FieldC>
    <FieldD>Plant</FieldD>
    <FieldE>Plant Name</FieldE>
    <FieldF>MRP</FieldF>
    <FieldG>Cal/Week Format</FieldG>
  </Header>
  <Details>
    <FieldA>200905</FieldA>
    <FieldC>EA</FieldC>
    <FieldD>7A01</FieldD>
    <FieldE>Abbotsford Brewery</FieldE>
    <FieldF>0</FieldF>
    <FieldG>06.2019</FieldG>
  </Details>
  <Details>
    <FieldA>200905</FieldA>
    <FieldC>EA</FieldC>
    <FieldD>7A01</FieldD>
    <FieldE>Abbotsford Brewery</FieldE>
    <FieldF>0</FieldF>
    <FieldG>07.2019</FieldG>
  </Details>
  <Details>
    <FieldA>200905</FieldA>
    <FieldC>EA</FieldC>
    <FieldD>7A01</FieldD>
    <FieldE>Abbotsford Brewery</FieldE>
    <FieldF>0</FieldF>
    <FieldG>08.2019</FieldG>
  </Details>
  <Details>
    <FieldA>200905</FieldA>
    <FieldC>EA</FieldC>
    <FieldD>7A01</FieldD>
    <FieldE>Abbotsford Brewery</FieldE>
    <FieldF>27000</FieldF>
    <FieldG>09.2019</FieldG>
  </Details>
  <Details>
    <FieldA>200905</FieldA>
    <FieldC>EA</FieldC>
    <FieldD>7A01</FieldD>
    <FieldE>Abbotsford Brewery</FieldE>
    <FieldF>0</FieldF>
    <FieldG>10.2019</FieldG>
  </Details>
  <Details>
    <FieldA>200905</FieldA>
    <FieldC>EA</FieldC>
    <FieldD>7A01</FieldD>
    <FieldE>Abbotsford Brewery</FieldE>
    <FieldF>108000</FieldF>
    <FieldG>11.2019</FieldG>
  </Details>
  <Details>
    <FieldA>200905</FieldA>
    <FieldC>EA</FieldC>
    <FieldD>7A01</FieldD>
    <FieldE>Abbotsford Brewery</FieldE>
    <FieldF>81000</FieldF>
    <FieldG>12.2019</FieldG>
  </Details>
  <Details>
    <FieldA>200905</FieldA>
    <FieldC>EA</FieldC>
    <FieldD>7A01</FieldD>
    <FieldE>Abbotsford Brewery</FieldE>
    <FieldF>81000</FieldF>
    <FieldG>13.2019</FieldG>
  </Details>
  <Details>
    <FieldA>200905</FieldA>
    <FieldC>EA</FieldC>
    <FieldD>7A01</FieldD>
    <FieldE>Abbotsford Brewery</FieldE>
    <FieldF>108000</FieldF>
    <FieldG>14.2019</FieldG>
  </Details>
  <Details>
    <FieldA>200905</FieldA>
    <FieldC>EA</FieldC>
    <FieldD>7A01</FieldD>
    <FieldE>Abbotsford Brewery</FieldE>
    <FieldF>54000</FieldF>
    <FieldG>15.2019</FieldG>
  </Details>
  <Details>
    <FieldA>200905</FieldA>
    <FieldC>EA</FieldC>
    <FieldD>7A01</FieldD>
    <FieldE>Abbotsford Brewery</FieldE>
    <FieldF>27000</FieldF>
    <FieldG>16.2019</FieldG>
  </Details>
  <Details>
    <FieldA>200905</FieldA>
    <FieldC>EA</FieldC>
    <FieldD>7A01</FieldD>
    <FieldE>Abbotsford Brewery</FieldE>
    <FieldF>54000</FieldF>
    <FieldG>17.2019</FieldG>
  </Details>
  <Details>
    <FieldA>200905</FieldA>
    <FieldC>EA</FieldC>
    <FieldD>7A01</FieldD>
    <FieldE>Abbotsford Brewery</FieldE>
    <FieldF>81000</FieldF>
    <FieldG>18.2019</FieldG>
  </Details>
  <Details>
    <FieldA>200905</FieldA>
    <FieldC>EA</FieldC>
    <FieldD>7A01</FieldD>
    <FieldE>Abbotsford Brewery</FieldE>
    <FieldF>27000</FieldF>
    <FieldG>19.2019</FieldG>
  </Details>
  <Details>
    <FieldA>200905</FieldA>
    <FieldC>EA</FieldC>
    <FieldD>7A02</FieldD>
    <FieldE>Yatala Brewery</FieldE>
    <FieldF>0</FieldF>
    <FieldG>06.2019</FieldG>
  </Details>
  <Details>
    <FieldA>200905</FieldA>
    <FieldC>EA</FieldC>
    <FieldD>7A02</FieldD>
    <FieldE>Yatala Brewery</FieldE>
    <FieldF>0</FieldF>
    <FieldG>07.2019</FieldG>
  </Details>
  <Details>
    <FieldA>200905</FieldA>
    <FieldC>EA</FieldC>
    <FieldD>7A02</FieldD>
    <FieldE>Yatala Brewery</FieldE>
    <FieldF>0</FieldF>
    <FieldG>08.2019</FieldG>
  </Details>
  <Details>
    <FieldA>200905</FieldA>
    <FieldC>EA</FieldC>
    <FieldD>7A02</FieldD>
    <FieldE>Yatala Brewery</FieldE>
    <FieldF>243000</FieldF>
    <FieldG>09.2019</FieldG>
  </Details>
  <Details>
    <FieldA>200905</FieldA>
    <FieldC>EA</FieldC>
    <FieldD>7A02</FieldD>
    <FieldE>Yatala Brewery</FieldE>
    <FieldF>0</FieldF>
    <FieldG>10.2019</FieldG>
  </Details>
  <Details>
    <FieldA>200905</FieldA>
    <FieldC>EA</FieldC>
    <FieldD>7A02</FieldD>
    <FieldE>Yatala Brewery</FieldE>
    <FieldF>243000</FieldF>
    <FieldG>11.2019</FieldG>
  </Details>
  <Details>
    <FieldA>200905</FieldA>
    <FieldC>EA</FieldC>
    <FieldD>7A02</FieldD>
    <FieldE>Yatala Brewery</FieldE>
    <FieldF>189000</FieldF>
    <FieldG>12.2019</FieldG>
  </Details>
  <Details>
    <FieldA>200905</FieldA>
    <FieldC>EA</FieldC>
    <FieldD>7A02</FieldD>
    <FieldE>Yatala Brewery</FieldE>
    <FieldF>108000</FieldF>
    <FieldG>13.2019</FieldG>
  </Details>
  <Details>
    <FieldA>200905</FieldA>
    <FieldC>EA</FieldC>
    <FieldD>7A02</FieldD>
    <FieldE>Yatala Brewery</FieldE>
    <FieldF>270000</FieldF>
    <FieldG>14.2019</FieldG>
  </Details>
  <Details>
    <FieldA>200905</FieldA>
    <FieldC>EA</FieldC>
    <FieldD>7A02</FieldD>
    <FieldE>Yatala Brewery</FieldE>
    <FieldF>135000</FieldF>
    <FieldG>15.2019</FieldG>
  </Details>
  <Details>
    <FieldA>200905</FieldA>
    <FieldC>EA</FieldC>
    <FieldD>7A02</FieldD>
    <FieldE>Yatala Brewery</FieldE>
    <FieldF>135000</FieldF>
    <FieldG>16.2019</FieldG>
  </Details>
  <Details>
    <FieldA>200905</FieldA>
    <FieldC>EA</FieldC>
    <FieldD>7A02</FieldD>
    <FieldE>Yatala Brewery</FieldE>
    <FieldF>81000</FieldF>
    <FieldG>17.2019</FieldG>
  </Details>
  <Details>
    <FieldA>200905</FieldA>
    <FieldC>EA</FieldC>
    <FieldD>7A02</FieldD>
    <FieldE>Yatala Brewery</FieldE>
    <FieldF>216000</FieldF>
    <FieldG>18.2019</FieldG>
  </Details>
  <Details>
    <FieldA>200905</FieldA>
    <FieldC>EA</FieldC>
    <FieldD>7A02</FieldD>
    <FieldE>Yatala Brewery</FieldE>
    <FieldF>135000</FieldF>
    <FieldG>19.2019</FieldG>
  </Details>
  <Details>
    <FieldA>200906</FieldA>
    <FieldC>EA</FieldC>
    <FieldD>7A02</FieldD>
    <FieldE>Yatala Brewery</FieldE>
    <FieldF>0</FieldF>
    <FieldG>06.2019</FieldG>
  </Details>
  <Details>
    <FieldA>200906</FieldA>
    <FieldC>EA</FieldC>
    <FieldD>7A02</FieldD>
    <FieldE>Yatala Brewery</FieldE>
    <FieldF>0</FieldF>
    <FieldG>07.2019</FieldG>
  </Details>
  <Details>
    <FieldA>200906</FieldA>
    <FieldC>EA</FieldC>
    <FieldD>7A02</FieldD>
    <FieldE>Yatala Brewery</FieldE>
    <FieldF>0</FieldF>
    <FieldG>08.2019</FieldG>
  </Details>
  <Details>
    <FieldA>200906</FieldA>
    <FieldC>EA</FieldC>
    <FieldD>7A02</FieldD>
    <FieldE>Yatala Brewery</FieldE>
    <FieldF>0</FieldF>
    <FieldG>09.2019</FieldG>
  </Details>
  <Details>
    <FieldA>200906</FieldA>
    <FieldC>EA</FieldC>
    <FieldD>7A02</FieldD>
    <FieldE>Yatala Brewery</FieldE>
    <FieldF>0</FieldF>
    <FieldG>10.2019</FieldG>
  </Details>
  <Details>
    <FieldA>200906</FieldA>
    <FieldC>EA</FieldC>
    <FieldD>7A02</FieldD>
    <FieldE>Yatala Brewery</FieldE>
    <FieldF>0</FieldF>
    <FieldG>11.2019</FieldG>
  </Details>
  <Details>
    <FieldA>200906</FieldA>
    <FieldC>EA</FieldC>
    <FieldD>7A02</FieldD>
    <FieldE>Yatala Brewery</FieldE>
    <FieldF>0</FieldF>
    <FieldG>12.2019</FieldG>
  </Details>
  <Details>
    <FieldA>200906</FieldA>
    <FieldC>EA</FieldC>
    <FieldD>7A02</FieldD>
    <FieldE>Yatala Brewery</FieldE>
    <FieldF>0</FieldF>
    <FieldG>13.2019</FieldG>
  </Details>
  <Details>
    <FieldA>200906</FieldA>
    <FieldC>EA</FieldC>
    <FieldD>7A02</FieldD>
    <FieldE>Yatala Brewery</FieldE>
    <FieldF>0</FieldF>
    <FieldG>14.2019</FieldG>
  </Details>
  <Details>
    <FieldA>200906</FieldA>
    <FieldC>EA</FieldC>
    <FieldD>7A02</FieldD>
    <FieldE>Yatala Brewery</FieldE>
    <FieldF>0</FieldF>
    <FieldG>15.2019</FieldG>
  </Details>
  <Details>
    <FieldA>200906</FieldA>
    <FieldC>EA</FieldC>
    <FieldD>7A02</FieldD>
    <FieldE>Yatala Brewery</FieldE>
    <FieldF>0</FieldF>
    <FieldG>16.2019</FieldG>
  </Details>
  <Details>
    <FieldA>200906</FieldA>
    <FieldC>EA</FieldC>
    <FieldD>7A02</FieldD>
    <FieldE>Yatala Brewery</FieldE>
    <FieldF>0</FieldF>
    <FieldG>17.2019</FieldG>
  </Details>
  <Details>
    <FieldA>200906</FieldA>
    <FieldC>EA</FieldC>
    <FieldD>7A02</FieldD>
    <FieldE>Yatala Brewery</FieldE>
    <FieldF>0</FieldF>
    <FieldG>18.2019</FieldG>
  </Details>
  <Details>
    <FieldA>200906</FieldA>
    <FieldC>EA</FieldC>
    <FieldD>7A02</FieldD>
    <FieldE>Yatala Brewery</FieldE>
    <FieldF>0</FieldF>
    <FieldG>19.2019</FieldG>
  </Details>
  <Details>
    <FieldA>200964</FieldA>
    <FieldC>EA</FieldC>
    <FieldD>7A01</FieldD>
    <FieldE>Abbotsford Brewery</FieldE>
    <FieldF>0</FieldF>
    <FieldG>06.2019</FieldG>
  </Details>
  <Details>
    <FieldA>200964</FieldA>
    <FieldC>EA</FieldC>
    <FieldD>7A01</FieldD>
    <FieldE>Abbotsford Brewery</FieldE>
    <FieldF>0</FieldF>
    <FieldG>07.2019</FieldG>
  </Details>
  <Details>
    <FieldA>200964</FieldA>
    <FieldC>EA</FieldC>
    <FieldD>7A01</FieldD>
    <FieldE>Abbotsford Brewery</FieldE>
    <FieldF>0</FieldF>
    <FieldG>08.2019</FieldG>
  </Details>
  <Details>
    <FieldA>200964</FieldA>
    <FieldC>EA</FieldC>
    <FieldD>7A01</FieldD>
    <FieldE>Abbotsford Brewery</FieldE>
    <FieldF>0</FieldF>
    <FieldG>09.2019</FieldG>
  </Details>
  <Details>
    <FieldA>200964</FieldA>
    <FieldC>EA</FieldC>
    <FieldD>7A01</FieldD>
    <FieldE>Abbotsford Brewery</FieldE>
    <FieldF>0</FieldF>
    <FieldG>10.2019</FieldG>
  </Details>
  <Details>
    <FieldA>200964</FieldA>
    <FieldC>EA</FieldC>
    <FieldD>7A01</FieldD>
    <FieldE>Abbotsford Brewery</FieldE>
    <FieldF>0</FieldF>
    <FieldG>11.2019</FieldG>
  </Details>
  <Details>
    <FieldA>200964</FieldA>
    <FieldC>EA</FieldC>
    <FieldD>7A01</FieldD>
    <FieldE>Abbotsford Brewery</FieldE>
    <FieldF>0</FieldF>
    <FieldG>12.2019</FieldG>
  </Details>
  <Details>
    <FieldA>200964</FieldA>
    <FieldC>EA</FieldC>
    <FieldD>7A01</FieldD>
    <FieldE>Abbotsford Brewery</FieldE>
    <FieldF>0</FieldF>
    <FieldG>13.2019</FieldG>
  </Details>
  <Details>
    <FieldA>200964</FieldA>
    <FieldC>EA</FieldC>
    <FieldD>7A01</FieldD>
    <FieldE>Abbotsford Brewery</FieldE>
    <FieldF>0</FieldF>
    <FieldG>14.2019</FieldG>
  </Details>
  <Details>
    <FieldA>200964</FieldA>
    <FieldC>EA</FieldC>
    <FieldD>7A01</FieldD>
    <FieldE>Abbotsford Brewery</FieldE>
    <FieldF>0</FieldF>
    <FieldG>15.2019</FieldG>
  </Details>
  <Details>
    <FieldA>200964</FieldA>
    <FieldC>EA</FieldC>
    <FieldD>7A01</FieldD>
    <FieldE>Abbotsford Brewery</FieldE>
    <FieldF>0</FieldF>
    <FieldG>16.2019</FieldG>
  </Details>
  <Details>
    <FieldA>200964</FieldA>
    <FieldC>EA</FieldC>
    <FieldD>7A01</FieldD>
    <FieldE>Abbotsford Brewery</FieldE>
    <FieldF>0</FieldF>
    <FieldG>17.2019</FieldG>
  </Details>
  <Details>
    <FieldA>200964</FieldA>
    <FieldC>EA</FieldC>
    <FieldD>7A01</FieldD>
    <FieldE>Abbotsford Brewery</FieldE>
    <FieldF>0</FieldF>
    <FieldG>18.2019</FieldG>
  </Details>
  <Details>
    <FieldA>200964</FieldA>
    <FieldC>EA</FieldC>
    <FieldD>7A01</FieldD>
    <FieldE>Abbotsford Brewery</FieldE>
    <FieldF>0</FieldF>
    <FieldG>19.2019</FieldG>
  </Details>
  <Details>
    <FieldA>223383</FieldA>
    <FieldC>EA</FieldC>
    <FieldD>7A02</FieldD>
    <FieldE>Yatala Brewery</FieldE>
    <FieldF>0</FieldF>
    <FieldG>06.2019</FieldG>
  </Details>
  <Details>
    <FieldA>223383</FieldA>
    <FieldC>EA</FieldC>
    <FieldD>7A02</FieldD>
    <FieldE>Yatala Brewery</FieldE>
    <FieldF>0</FieldF>
    <FieldG>07.2019</FieldG>
  </Details>
  <Details>
    <FieldA>223383</FieldA>
    <FieldC>EA</FieldC>
    <FieldD>7A02</FieldD>
    <FieldE>Yatala Brewery</FieldE>
    <FieldF>0</FieldF>
    <FieldG>08.2019</FieldG>
  </Details>
  <Details>
    <FieldA>223383</FieldA>
    <FieldC>EA</FieldC>
    <FieldD>7A02</FieldD>
    <FieldE>Yatala Brewery</FieldE>
    <FieldF>24000</FieldF>
    <FieldG>09.2019</FieldG>
  </Details>
  <Details>
    <FieldA>223383</FieldA>
    <FieldC>EA</FieldC>
    <FieldD>7A02</FieldD>
    <FieldE>Yatala Brewery</FieldE>
    <FieldF>0</FieldF>
    <FieldG>10.2019</FieldG>
  </Details>
  <Details>
    <FieldA>223383</FieldA>
    <FieldC>EA</FieldC>
    <FieldD>7A02</FieldD>
    <FieldE>Yatala Brewery</FieldE>
    <FieldF>0</FieldF>
    <FieldG>11.2019</FieldG>
  </Details>
  <Details>
    <FieldA>223383</FieldA>
    <FieldC>EA</FieldC>
    <FieldD>7A02</FieldD>
    <FieldE>Yatala Brewery</FieldE>
    <FieldF>0</FieldF>
    <FieldG>12.2019</FieldG>
  </Details>
  <Details>
    <FieldA>223383</FieldA>
    <FieldC>EA</FieldC>
    <FieldD>7A02</FieldD>
    <FieldE>Yatala Brewery</FieldE>
    <FieldF>0</FieldF>
    <FieldG>13.2019</FieldG>
  </Details>
  <Details>
    <FieldA>223383</FieldA>
    <FieldC>EA</FieldC>
    <FieldD>7A02</FieldD>
    <FieldE>Yatala Brewery</FieldE>
    <FieldF>0</FieldF>
    <FieldG>14.2019</FieldG>
  </Details>
  <Details>
    <FieldA>223383</FieldA>
    <FieldC>EA</FieldC>
    <FieldD>7A02</FieldD>
    <FieldE>Yatala Brewery</FieldE>
    <FieldF>0</FieldF>
    <FieldG>15.2019</FieldG>
  </Details>
  <Details>
    <FieldA>223383</FieldA>
    <FieldC>EA</FieldC>
    <FieldD>7A02</FieldD>
    <FieldE>Yatala Brewery</FieldE>
    <FieldF>0</FieldF>
    <FieldG>16.2019</FieldG>
  </Details>
  <Details>
    <FieldA>223383</FieldA>
    <FieldC>EA</FieldC>
    <FieldD>7A02</FieldD>
    <FieldE>Yatala Brewery</FieldE>
    <FieldF>0</FieldF>
    <FieldG>17.2019</FieldG>
  </Details>
  <Details>
    <FieldA>223383</FieldA>
    <FieldC>EA</FieldC>
    <FieldD>7A02</FieldD>
    <FieldE>Yatala Brewery</FieldE>
    <FieldF>0</FieldF>
    <FieldG>18.2019</FieldG>
  </Details>
  <Details>
    <FieldA>223383</FieldA>
    <FieldC>EA</FieldC>
    <FieldD>7A02</FieldD>
    <FieldE>Yatala Brewery</FieldE>
    <FieldF>0</FieldF>
    <FieldG>19.2019</FieldG>
  </Details>
  <Details>
    <FieldA>224113</FieldA>
    <FieldC>EA</FieldC>
    <FieldD>7A02</FieldD>
    <FieldE>Yatala Brewery</FieldE>
    <FieldF>0</FieldF>
    <FieldG>06.2019</FieldG>
  </Details>
  <Details>
    <FieldA>224113</FieldA>
    <FieldC>EA</FieldC>
    <FieldD>7A02</FieldD>
    <FieldE>Yatala Brewery</FieldE>
    <FieldF>3000</FieldF>
    <FieldG>07.2019</FieldG>
  </Details>
  <Details>
    <FieldA>224113</FieldA>
    <FieldC>EA</FieldC>
    <FieldD>7A02</FieldD>
    <FieldE>Yatala Brewery</FieldE>
    <FieldF>0</FieldF>
    <FieldG>08.2019</FieldG>
  </Details>
  <Details>
    <FieldA>224113</FieldA>
    <FieldC>EA</FieldC>
    <FieldD>7A02</FieldD>
    <FieldE>Yatala Brewery</FieldE>
    <FieldF>0</FieldF>
    <FieldG>09.2019</FieldG>
  </Details>
  <Details>
    <FieldA>224113</FieldA>
    <FieldC>EA</FieldC>
    <FieldD>7A02</FieldD>
    <FieldE>Yatala Brewery</FieldE>
    <FieldF>0</FieldF>
    <FieldG>10.2019</FieldG>
  </Details>
  <Details>
    <FieldA>224113</FieldA>
    <FieldC>EA</FieldC>
    <FieldD>7A02</FieldD>
    <FieldE>Yatala Brewery</FieldE>
    <FieldF>0</FieldF>
    <FieldG>11.2019</FieldG>
  </Details>
  <Details>
    <FieldA>224113</FieldA>
    <FieldC>EA</FieldC>
    <FieldD>7A02</FieldD>
    <FieldE>Yatala Brewery</FieldE>
    <FieldF>0</FieldF>
    <FieldG>12.2019</FieldG>
  </Details>
  <Details>
    <FieldA>224113</FieldA>
    <FieldC>EA</FieldC>
    <FieldD>7A02</FieldD>
    <FieldE>Yatala Brewery</FieldE>
    <FieldF>0</FieldF>
    <FieldG>13.2019</FieldG>
  </Details>
  <Details>
    <FieldA>224113</FieldA>
    <FieldC>EA</FieldC>
    <FieldD>7A02</FieldD>
    <FieldE>Yatala Brewery</FieldE>
    <FieldF>0</FieldF>
    <FieldG>14.2019</FieldG>
  </Details>
  <Details>
    <FieldA>224113</FieldA>
    <FieldC>EA</FieldC>
    <FieldD>7A02</FieldD>
    <FieldE>Yatala Brewery</FieldE>
    <FieldF>0</FieldF>
    <FieldG>15.2019</FieldG>
  </Details>
  <Details>
    <FieldA>224113</FieldA>
    <FieldC>EA</FieldC>
    <FieldD>7A02</FieldD>
    <FieldE>Yatala Brewery</FieldE>
    <FieldF>0</FieldF>
    <FieldG>16.2019</FieldG>
  </Details>
  <Details>
    <FieldA>224113</FieldA>
    <FieldC>EA</FieldC>
    <FieldD>7A02</FieldD>
    <FieldE>Yatala Brewery</FieldE>
    <FieldF>0</FieldF>
    <FieldG>17.2019</FieldG>
  </Details>
  <Details>
    <FieldA>224113</FieldA>
    <FieldC>EA</FieldC>
    <FieldD>7A02</FieldD>
    <FieldE>Yatala Brewery</FieldE>
    <FieldF>0</FieldF>
    <FieldG>18.2019</FieldG>
  </Details>
  <Details>
    <FieldA>224113</FieldA>
    <FieldC>EA</FieldC>
    <FieldD>7A02</FieldD>
    <FieldE>Yatala Brewery</FieldE>
    <FieldF>0</FieldF>
    <FieldG>19.2019</FieldG>
  </Details>
  <Details>
    <FieldA>236994</FieldA>
    <FieldC>EA</FieldC>
    <FieldD>7A02</FieldD>
    <FieldE>Yatala Brewery</FieldE>
    <FieldF>0</FieldF>
    <FieldG>06.2019</FieldG>
  </Details>
  <Details>
    <FieldA>236994</FieldA>
    <FieldC>EA</FieldC>
    <FieldD>7A02</FieldD>
    <FieldE>Yatala Brewery</FieldE>
    <FieldF>0</FieldF>
    <FieldG>07.2019</FieldG>
  </Details>
  <Details>
    <FieldA>236994</FieldA>
    <FieldC>EA</FieldC>
    <FieldD>7A02</FieldD>
    <FieldE>Yatala Brewery</FieldE>
    <FieldF>24000</FieldF>
    <FieldG>08.2019</FieldG>
  </Details>
  <Details>
    <FieldA>236994</FieldA>
    <FieldC>EA</FieldC>
    <FieldD>7A02</FieldD>
    <FieldE>Yatala Brewery</FieldE>
    <FieldF>0</FieldF>
    <FieldG>09.2019</FieldG>
  </Details>
  <Details>
    <FieldA>236994</FieldA>
    <FieldC>EA</FieldC>
    <FieldD>7A02</FieldD>
    <FieldE>Yatala Brewery</FieldE>
    <FieldF>0</FieldF>
    <FieldG>10.2019</FieldG>
  </Details>
  <Details>
    <FieldA>236994</FieldA>
    <FieldC>EA</FieldC>
    <FieldD>7A02</FieldD>
    <FieldE>Yatala Brewery</FieldE>
    <FieldF>0</FieldF>
    <FieldG>11.2019</FieldG>
  </Details>
  <Details>
    <FieldA>236994</FieldA>
    <FieldC>EA</FieldC>
    <FieldD>7A02</FieldD>
    <FieldE>Yatala Brewery</FieldE>
    <FieldF>0</FieldF>
    <FieldG>12.2019</FieldG>
  </Details>
  <Details>
    <FieldA>236994</FieldA>
    <FieldC>EA</FieldC>
    <FieldD>7A02</FieldD>
    <FieldE>Yatala Brewery</FieldE>
    <FieldF>0</FieldF>
    <FieldG>13.2019</FieldG>
  </Details>
  <Details>
    <FieldA>236994</FieldA>
    <FieldC>EA</FieldC>
    <FieldD>7A02</FieldD>
    <FieldE>Yatala Brewery</FieldE>
    <FieldF>0</FieldF>
    <FieldG>14.2019</FieldG>
  </Details>
  <Details>
    <FieldA>236994</FieldA>
    <FieldC>EA</FieldC>
    <FieldD>7A02</FieldD>
    <FieldE>Yatala Brewery</FieldE>
    <FieldF>0</FieldF>
    <FieldG>15.2019</FieldG>
  </Details>
  <Details>
    <FieldA>236994</FieldA>
    <FieldC>EA</FieldC>
    <FieldD>7A02</FieldD>
    <FieldE>Yatala Brewery</FieldE>
    <FieldF>0</FieldF>
    <FieldG>16.2019</FieldG>
  </Details>
  <Details>
    <FieldA>236994</FieldA>
    <FieldC>EA</FieldC>
    <FieldD>7A02</FieldD>
    <FieldE>Yatala Brewery</FieldE>
    <FieldF>0</FieldF>
    <FieldG>17.2019</FieldG>
  </Details>
  <Details>
    <FieldA>236994</FieldA>
    <FieldC>EA</FieldC>
    <FieldD>7A02</FieldD>
    <FieldE>Yatala Brewery</FieldE>
    <FieldF>0</FieldF>
    <FieldG>18.2019</FieldG>
  </Details>
  <Details>
    <FieldA>236994</FieldA>
    <FieldC>EA</FieldC>
    <FieldD>7A02</FieldD>
    <FieldE>Yatala Brewery</FieldE>
    <FieldF>0</FieldF>
    <FieldG>19.2019</FieldG>
  </Details>
  <Details>
    <FieldA>262899</FieldA>
    <FieldC>EA</FieldC>
    <FieldD>7A02</FieldD>
    <FieldE>Yatala Brewery</FieldE>
    <FieldF>0</FieldF>
    <FieldG>06.2019</FieldG>
  </Details>
  <Details>
    <FieldA>262899</FieldA>
    <FieldC>EA</FieldC>
    <FieldD>7A02</FieldD>
    <FieldE>Yatala Brewery</FieldE>
    <FieldF>2016</FieldF>
    <FieldG>07.2019</FieldG>
  </Details>
  <Details>
    <FieldA>262899</FieldA>
    <FieldC>EA</FieldC>
    <FieldD>7A02</FieldD>
    <FieldE>Yatala Brewery</FieldE>
    <FieldF>0</FieldF>
    <FieldG>08.2019</FieldG>
  </Details>
  <Details>
    <FieldA>262899</FieldA>
    <FieldC>EA</FieldC>
    <FieldD>7A02</FieldD>
    <FieldE>Yatala Brewery</FieldE>
    <FieldF>0</FieldF>
    <FieldG>09.2019</FieldG>
  </Details>
  <Details>
    <FieldA>262899</FieldA>
    <FieldC>EA</FieldC>
    <FieldD>7A02</FieldD>
    <FieldE>Yatala Brewery</FieldE>
    <FieldF>0</FieldF>
    <FieldG>10.2019</FieldG>
  </Details>
  <Details>
    <FieldA>262899</FieldA>
    <FieldC>EA</FieldC>
    <FieldD>7A02</FieldD>
    <FieldE>Yatala Brewery</FieldE>
    <FieldF>0</FieldF>
    <FieldG>11.2019</FieldG>
  </Details>
  <Details>
    <FieldA>262899</FieldA>
    <FieldC>EA</FieldC>
    <FieldD>7A02</FieldD>
    <FieldE>Yatala Brewery</FieldE>
    <FieldF>0</FieldF>
    <FieldG>12.2019</FieldG>
  </Details>
  <Details>
    <FieldA>262899</FieldA>
    <FieldC>EA</FieldC>
    <FieldD>7A02</FieldD>
    <FieldE>Yatala Brewery</FieldE>
    <FieldF>0</FieldF>
    <FieldG>13.2019</FieldG>
  </Details>
  <Details>
    <FieldA>262899</FieldA>
    <FieldC>EA</FieldC>
    <FieldD>7A02</FieldD>
    <FieldE>Yatala Brewery</FieldE>
    <FieldF>0</FieldF>
    <FieldG>14.2019</FieldG>
  </Details>
  <Details>
    <FieldA>262899</FieldA>
    <FieldC>EA</FieldC>
    <FieldD>7A02</FieldD>
    <FieldE>Yatala Brewery</FieldE>
    <FieldF>0</FieldF>
    <FieldG>15.2019</FieldG>
  </Details>
  <Details>
    <FieldA>262899</FieldA>
    <FieldC>EA</FieldC>
    <FieldD>7A02</FieldD>
    <FieldE>Yatala Brewery</FieldE>
    <FieldF>0</FieldF>
    <FieldG>16.2019</FieldG>
  </Details>
  <Details>
    <FieldA>262899</FieldA>
    <FieldC>EA</FieldC>
    <FieldD>7A02</FieldD>
    <FieldE>Yatala Brewery</FieldE>
    <FieldF>10080</FieldF>
    <FieldG>17.2019</FieldG>
  </Details>
  <Details>
    <FieldA>262899</FieldA>
    <FieldC>EA</FieldC>
    <FieldD>7A02</FieldD>
    <FieldE>Yatala Brewery</FieldE>
    <FieldF>0</FieldF>
    <FieldG>18.2019</FieldG>
  </Details>
  <Details>
    <FieldA>262899</FieldA>
    <FieldC>EA</FieldC>
    <FieldD>7A02</FieldD>
    <FieldE>Yatala Brewery</FieldE>
    <FieldF>0</FieldF>
    <FieldG>19.2019</FieldG>
  </Details>
  <Details>
    <FieldA>263040</FieldA>
    <FieldC>EA</FieldC>
    <FieldD>7A01</FieldD>
    <FieldE>Abbotsford Brewery</FieldE>
    <FieldF>0</FieldF>
    <FieldG>06.2019</FieldG>
  </Details>
  <Details>
    <FieldA>263040</FieldA>
    <FieldC>EA</FieldC>
    <FieldD>7A01</FieldD>
    <FieldE>Abbotsford Brewery</FieldE>
    <FieldF>2016</FieldF>
    <FieldG>07.2019</FieldG>
  </Details>
  <Details>
    <FieldA>263040</FieldA>
    <FieldC>EA</FieldC>
    <FieldD>7A01</FieldD>
    <FieldE>Abbotsford Brewery</FieldE>
    <FieldF>40320</FieldF>
    <FieldG>08.2019</FieldG>
  </Details>
  <Details>
    <FieldA>263040</FieldA>
    <FieldC>EA</FieldC>
    <FieldD>7A01</FieldD>
    <FieldE>Abbotsford Brewery</FieldE>
    <FieldF>0</FieldF>
    <FieldG>09.2019</FieldG>
  </Details>
  <Details>
    <FieldA>263040</FieldA>
    <FieldC>EA</FieldC>
    <FieldD>7A01</FieldD>
    <FieldE>Abbotsford Brewery</FieldE>
    <FieldF>0</FieldF>
    <FieldG>10.2019</FieldG>
  </Details>
  <Details>
    <FieldA>263040</FieldA>
    <FieldC>EA</FieldC>
    <FieldD>7A01</FieldD>
    <FieldE>Abbotsford Brewery</FieldE>
    <FieldF>0</FieldF>
    <FieldG>11.2019</FieldG>
  </Details>
  <Details>
    <FieldA>263040</FieldA>
    <FieldC>EA</FieldC>
    <FieldD>7A01</FieldD>
    <FieldE>Abbotsford Brewery</FieldE>
    <FieldF>0</FieldF>
    <FieldG>12.2019</FieldG>
  </Details>
  <Details>
    <FieldA>263040</FieldA>
    <FieldC>EA</FieldC>
    <FieldD>7A01</FieldD>
    <FieldE>Abbotsford Brewery</FieldE>
    <FieldF>0</FieldF>
    <FieldG>13.2019</FieldG>
  </Details>
  <Details>
    <FieldA>263040</FieldA>
    <FieldC>EA</FieldC>
    <FieldD>7A01</FieldD>
    <FieldE>Abbotsford Brewery</FieldE>
    <FieldF>0</FieldF>
    <FieldG>14.2019</FieldG>
  </Details>
  <Details>
    <FieldA>263040</FieldA>
    <FieldC>EA</FieldC>
    <FieldD>7A01</FieldD>
    <FieldE>Abbotsford Brewery</FieldE>
    <FieldF>10080</FieldF>
    <FieldG>15.2019</FieldG>
  </Details>
  <Details>
    <FieldA>263040</FieldA>
    <FieldC>EA</FieldC>
    <FieldD>7A01</FieldD>
    <FieldE>Abbotsford Brewery</FieldE>
    <FieldF>0</FieldF>
    <FieldG>16.2019</FieldG>
  </Details>
  <Details>
    <FieldA>263040</FieldA>
    <FieldC>EA</FieldC>
    <FieldD>7A01</FieldD>
    <FieldE>Abbotsford Brewery</FieldE>
    <FieldF>10080</FieldF>
    <FieldG>17.2019</FieldG>
  </Details>
  <Details>
    <FieldA>263040</FieldA>
    <FieldC>EA</FieldC>
    <FieldD>7A01</FieldD>
    <FieldE>Abbotsford Brewery</FieldE>
    <FieldF>0</FieldF>
    <FieldG>18.2019</FieldG>
  </Details>
  <Details>
    <FieldA>263040</FieldA>
    <FieldC>EA</FieldC>
    <FieldD>7A01</FieldD>
    <FieldE>Abbotsford Brewery</FieldE>
    <FieldF>20160</FieldF>
    <FieldG>19.2019</FieldG>
  </Details>
  <Details>
    <FieldA>265869</FieldA>
    <FieldC>EA</FieldC>
    <FieldD>7A01</FieldD>
    <FieldE>Abbotsford Brewery</FieldE>
    <FieldF>0</FieldF>
    <FieldG>06.2019</FieldG>
  </Details>
  <Details>
    <FieldA>265869</FieldA>
    <FieldC>EA</FieldC>
    <FieldD>7A01</FieldD>
    <FieldE>Abbotsford Brewery</FieldE>
    <FieldF>0</FieldF>
    <FieldG>07.2019</FieldG>
  </Details>
  <Details>
    <FieldA>265869</FieldA>
    <FieldC>EA</FieldC>
    <FieldD>7A01</FieldD>
    <FieldE>Abbotsford Brewery</FieldE>
    <FieldF>0</FieldF>
    <FieldG>08.2019</FieldG>
  </Details>
  <Details>
    <FieldA>265869</FieldA>
    <FieldC>EA</FieldC>
    <FieldD>7A01</FieldD>
    <FieldE>Abbotsford Brewery</FieldE>
    <FieldF>0</FieldF>
    <FieldG>09.2019</FieldG>
  </Details>
  <Details>
    <FieldA>265869</FieldA>
    <FieldC>EA</FieldC>
    <FieldD>7A01</FieldD>
    <FieldE>Abbotsford Brewery</FieldE>
    <FieldF>0</FieldF>
    <FieldG>10.2019</FieldG>
  </Details>
  <Details>
    <FieldA>265869</FieldA>
    <FieldC>EA</FieldC>
    <FieldD>7A01</FieldD>
    <FieldE>Abbotsford Brewery</FieldE>
    <FieldF>8064</FieldF>
    <FieldG>11.2019</FieldG>
  </Details>
  <Details>
    <FieldA>265869</FieldA>
    <FieldC>EA</FieldC>
    <FieldD>7A01</FieldD>
    <FieldE>Abbotsford Brewery</FieldE>
    <FieldF>0</FieldF>
    <FieldG>12.2019</FieldG>
  </Details>
  <Details>
    <FieldA>265869</FieldA>
    <FieldC>EA</FieldC>
    <FieldD>7A01</FieldD>
    <FieldE>Abbotsford Brewery</FieldE>
    <FieldF>0</FieldF>
    <FieldG>13.2019</FieldG>
  </Details>
  <Details>
    <FieldA>265869</FieldA>
    <FieldC>EA</FieldC>
    <FieldD>7A01</FieldD>
    <FieldE>Abbotsford Brewery</FieldE>
    <FieldF>0</FieldF>
    <FieldG>14.2019</FieldG>
  </Details>
  <Details>
    <FieldA>265869</FieldA>
    <FieldC>EA</FieldC>
    <FieldD>7A01</FieldD>
    <FieldE>Abbotsford Brewery</FieldE>
    <FieldF>0</FieldF>
    <FieldG>15.2019</FieldG>
  </Details>
  <Details>
    <FieldA>265869</FieldA>
    <FieldC>EA</FieldC>
    <FieldD>7A01</FieldD>
    <FieldE>Abbotsford Brewery</FieldE>
    <FieldF>0</FieldF>
    <FieldG>16.2019</FieldG>
  </Details>
  <Details>
    <FieldA>265869</FieldA>
    <FieldC>EA</FieldC>
    <FieldD>7A01</FieldD>
    <FieldE>Abbotsford Brewery</FieldE>
    <FieldF>10080</FieldF>
    <FieldG>17.2019</FieldG>
  </Details>
  <Details>
    <FieldA>265869</FieldA>
    <FieldC>EA</FieldC>
    <FieldD>7A01</FieldD>
    <FieldE>Abbotsford Brewery</FieldE>
    <FieldF>0</FieldF>
    <FieldG>18.2019</FieldG>
  </Details>
  <Details>
    <FieldA>265869</FieldA>
    <FieldC>EA</FieldC>
    <FieldD>7A01</FieldD>
    <FieldE>Abbotsford Brewery</FieldE>
    <FieldF>0</FieldF>
    <FieldG>19.2019</FieldG>
  </Details>
  <Details>
    <FieldA>266319</FieldA>
    <FieldC>EA</FieldC>
    <FieldD>7A02</FieldD>
    <FieldE>Yatala Brewery</FieldE>
    <FieldF>0</FieldF>
    <FieldG>06.2019</FieldG>
  </Details>
  <Details>
    <FieldA>266319</FieldA>
    <FieldC>EA</FieldC>
    <FieldD>7A02</FieldD>
    <FieldE>Yatala Brewery</FieldE>
    <FieldF>0</FieldF>
    <FieldG>07.2019</FieldG>
  </Details>
  <Details>
    <FieldA>266319</FieldA>
    <FieldC>EA</FieldC>
    <FieldD>7A02</FieldD>
    <FieldE>Yatala Brewery</FieldE>
    <FieldF>0</FieldF>
    <FieldG>08.2019</FieldG>
  </Details>
  <Details>
    <FieldA>266319</FieldA>
    <FieldC>EA</FieldC>
    <FieldD>7A02</FieldD>
    <FieldE>Yatala Brewery</FieldE>
    <FieldF>0</FieldF>
    <FieldG>09.2019</FieldG>
  </Details>
  <Details>
    <FieldA>266319</FieldA>
    <FieldC>EA</FieldC>
    <FieldD>7A02</FieldD>
    <FieldE>Yatala Brewery</FieldE>
    <FieldF>0</FieldF>
    <FieldG>10.2019</FieldG>
  </Details>
  <Details>
    <FieldA>266319</FieldA>
    <FieldC>EA</FieldC>
    <FieldD>7A02</FieldD>
    <FieldE>Yatala Brewery</FieldE>
    <FieldF>0</FieldF>
    <FieldG>11.2019</FieldG>
  </Details>
  <Details>
    <FieldA>266319</FieldA>
    <FieldC>EA</FieldC>
    <FieldD>7A02</FieldD>
    <FieldE>Yatala Brewery</FieldE>
    <FieldF>0</FieldF>
    <FieldG>12.2019</FieldG>
  </Details>
  <Details>
    <FieldA>266319</FieldA>
    <FieldC>EA</FieldC>
    <FieldD>7A02</FieldD>
    <FieldE>Yatala Brewery</FieldE>
    <FieldF>0</FieldF>
    <FieldG>13.2019</FieldG>
  </Details>
  <Details>
    <FieldA>266319</FieldA>
    <FieldC>EA</FieldC>
    <FieldD>7A02</FieldD>
    <FieldE>Yatala Brewery</FieldE>
    <FieldF>0</FieldF>
    <FieldG>14.2019</FieldG>
  </Details>
  <Details>
    <FieldA>266319</FieldA>
    <FieldC>EA</FieldC>
    <FieldD>7A02</FieldD>
    <FieldE>Yatala Brewery</FieldE>
    <FieldF>18144</FieldF>
    <FieldG>15.2019</FieldG>
  </Details>
  <Details>
    <FieldA>266319</FieldA>
    <FieldC>EA</FieldC>
    <FieldD>7A02</FieldD>
    <FieldE>Yatala Brewery</FieldE>
    <FieldF>0</FieldF>
    <FieldG>16.2019</FieldG>
  </Details>
  <Details>
    <FieldA>266319</FieldA>
    <FieldC>EA</FieldC>
    <FieldD>7A02</FieldD>
    <FieldE>Yatala Brewery</FieldE>
    <FieldF>0</FieldF>
    <FieldG>17.2019</FieldG>
  </Details>
  <Details>
    <FieldA>266319</FieldA>
    <FieldC>EA</FieldC>
    <FieldD>7A02</FieldD>
    <FieldE>Yatala Brewery</FieldE>
    <FieldF>0</FieldF>
    <FieldG>18.2019</FieldG>
  </Details>
  <Details>
    <FieldA>266319</FieldA>
    <FieldC>EA</FieldC>
    <FieldD>7A02</FieldD>
    <FieldE>Yatala Brewery</FieldE>
    <FieldF>0</FieldF>
    <FieldG>19.2019</FieldG>
  </Details>
  <Details>
    <FieldA>266320</FieldA>
    <FieldC>EA</FieldC>
    <FieldD>7A01</FieldD>
    <FieldE>Abbotsford Brewery</FieldE>
    <FieldF>0</FieldF>
    <FieldG>06.2019</FieldG>
  </Details>
  <Details>
    <FieldA>266320</FieldA>
    <FieldC>EA</FieldC>
    <FieldD>7A01</FieldD>
    <FieldE>Abbotsford Brewery</FieldE>
    <FieldF>0</FieldF>
    <FieldG>07.2019</FieldG>
  </Details>
  <Details>
    <FieldA>266320</FieldA>
    <FieldC>EA</FieldC>
    <FieldD>7A01</FieldD>
    <FieldE>Abbotsford Brewery</FieldE>
    <FieldF>0</FieldF>
    <FieldG>08.2019</FieldG>
  </Details>
  <Details>
    <FieldA>266320</FieldA>
    <FieldC>EA</FieldC>
    <FieldD>7A01</FieldD>
    <FieldE>Abbotsford Brewery</FieldE>
    <FieldF>0</FieldF>
    <FieldG>09.2019</FieldG>
  </Details>
  <Details>
    <FieldA>266320</FieldA>
    <FieldC>EA</FieldC>
    <FieldD>7A01</FieldD>
    <FieldE>Abbotsford Brewery</FieldE>
    <FieldF>0</FieldF>
    <FieldG>10.2019</FieldG>
  </Details>
  <Details>
    <FieldA>266320</FieldA>
    <FieldC>EA</FieldC>
    <FieldD>7A01</FieldD>
    <FieldE>Abbotsford Brewery</FieldE>
    <FieldF>22176</FieldF>
    <FieldG>11.2019</FieldG>
  </Details>
  <Details>
    <FieldA>266320</FieldA>
    <FieldC>EA</FieldC>
    <FieldD>7A01</FieldD>
    <FieldE>Abbotsford Brewery</FieldE>
    <FieldF>0</FieldF>
    <FieldG>12.2019</FieldG>
  </Details>
  <Details>
    <FieldA>266320</FieldA>
    <FieldC>EA</FieldC>
    <FieldD>7A01</FieldD>
    <FieldE>Abbotsford Brewery</FieldE>
    <FieldF>0</FieldF>
    <FieldG>13.2019</FieldG>
  </Details>
  <Details>
    <FieldA>266320</FieldA>
    <FieldC>EA</FieldC>
    <FieldD>7A01</FieldD>
    <FieldE>Abbotsford Brewery</FieldE>
    <FieldF>0</FieldF>
    <FieldG>14.2019</FieldG>
  </Details>
  <Details>
    <FieldA>266320</FieldA>
    <FieldC>EA</FieldC>
    <FieldD>7A01</FieldD>
    <FieldE>Abbotsford Brewery</FieldE>
    <FieldF>0</FieldF>
    <FieldG>15.2019</FieldG>
  </Details>
  <Details>
    <FieldA>266320</FieldA>
    <FieldC>EA</FieldC>
    <FieldD>7A01</FieldD>
    <FieldE>Abbotsford Brewery</FieldE>
    <FieldF>0</FieldF>
    <FieldG>16.2019</FieldG>
  </Details>
  <Details>
    <FieldA>266320</FieldA>
    <FieldC>EA</FieldC>
    <FieldD>7A01</FieldD>
    <FieldE>Abbotsford Brewery</FieldE>
    <FieldF>0</FieldF>
    <FieldG>17.2019</FieldG>
  </Details>
  <Details>
    <FieldA>266320</FieldA>
    <FieldC>EA</FieldC>
    <FieldD>7A01</FieldD>
    <FieldE>Abbotsford Brewery</FieldE>
    <FieldF>0</FieldF>
    <FieldG>18.2019</FieldG>
  </Details>
  <Details>
    <FieldA>266320</FieldA>
    <FieldC>EA</FieldC>
    <FieldD>7A01</FieldD>
    <FieldE>Abbotsford Brewery</FieldE>
    <FieldF>0</FieldF>
    <FieldG>19.2019</FieldG>
  </Details>
  <Details>
    <FieldA>266320</FieldA>
    <FieldC>EA</FieldC>
    <FieldD>7A02</FieldD>
    <FieldE>Yatala Brewery</FieldE>
    <FieldF>0</FieldF>
    <FieldG>06.2019</FieldG>
  </Details>
  <Details>
    <FieldA>266320</FieldA>
    <FieldC>EA</FieldC>
    <FieldD>7A02</FieldD>
    <FieldE>Yatala Brewery</FieldE>
    <FieldF>0</FieldF>
    <FieldG>07.2019</FieldG>
  </Details>
  <Details>
    <FieldA>266320</FieldA>
    <FieldC>EA</FieldC>
    <FieldD>7A02</FieldD>
    <FieldE>Yatala Brewery</FieldE>
    <FieldF>0</FieldF>
    <FieldG>08.2019</FieldG>
  </Details>
  <Details>
    <FieldA>266320</FieldA>
    <FieldC>EA</FieldC>
    <FieldD>7A02</FieldD>
    <FieldE>Yatala Brewery</FieldE>
    <FieldF>0</FieldF>
    <FieldG>09.2019</FieldG>
  </Details>
  <Details>
    <FieldA>266320</FieldA>
    <FieldC>EA</FieldC>
    <FieldD>7A02</FieldD>
    <FieldE>Yatala Brewery</FieldE>
    <FieldF>0</FieldF>
    <FieldG>10.2019</FieldG>
  </Details>
  <Details>
    <FieldA>266320</FieldA>
    <FieldC>EA</FieldC>
    <FieldD>7A02</FieldD>
    <FieldE>Yatala Brewery</FieldE>
    <FieldF>0</FieldF>
    <FieldG>11.2019</FieldG>
  </Details>
  <Details>
    <FieldA>266320</FieldA>
    <FieldC>EA</FieldC>
    <FieldD>7A02</FieldD>
    <FieldE>Yatala Brewery</FieldE>
    <FieldF>0</FieldF>
    <FieldG>12.2019</FieldG>
  </Details>
  <Details>
    <FieldA>266320</FieldA>
    <FieldC>EA</FieldC>
    <FieldD>7A02</FieldD>
    <FieldE>Yatala Brewery</FieldE>
    <FieldF>0</FieldF>
    <FieldG>13.2019</FieldG>
  </Details>
  <Details>
    <FieldA>266320</FieldA>
    <FieldC>EA</FieldC>
    <FieldD>7A02</FieldD>
    <FieldE>Yatala Brewery</FieldE>
    <FieldF>24192</FieldF>
    <FieldG>14.2019</FieldG>
  </Details>
  <Details>
    <FieldA>266320</FieldA>
    <FieldC>EA</FieldC>
    <FieldD>7A02</FieldD>
    <FieldE>Yatala Brewery</FieldE>
    <FieldF>0</FieldF>
    <FieldG>15.2019</FieldG>
  </Details>
  <Details>
    <FieldA>266320</FieldA>
    <FieldC>EA</FieldC>
    <FieldD>7A02</FieldD>
    <FieldE>Yatala Brewery</FieldE>
    <FieldF>0</FieldF>
    <FieldG>16.2019</FieldG>
  </Details>
  <Details>
    <FieldA>266320</FieldA>
    <FieldC>EA</FieldC>
    <FieldD>7A02</FieldD>
    <FieldE>Yatala Brewery</FieldE>
    <FieldF>0</FieldF>
    <FieldG>17.2019</FieldG>
  </Details>
  <Details>
    <FieldA>266320</FieldA>
    <FieldC>EA</FieldC>
    <FieldD>7A02</FieldD>
    <FieldE>Yatala Brewery</FieldE>
    <FieldF>0</FieldF>
    <FieldG>18.2019</FieldG>
  </Details>
  <Details>
    <FieldA>266320</FieldA>
    <FieldC>EA</FieldC>
    <FieldD>7A02</FieldD>
    <FieldE>Yatala Brewery</FieldE>
    <FieldF>0</FieldF>
    <FieldG>19.2019</FieldG>
  </Details>
  <Details>
    <FieldA>267247</FieldA>
    <FieldC>EA</FieldC>
    <FieldD>7A02</FieldD>
    <FieldE>Yatala Brewery</FieldE>
    <FieldF>0</FieldF>
    <FieldG>06.2019</FieldG>
  </Details>
  <Details>
    <FieldA>267247</FieldA>
    <FieldC>EA</FieldC>
    <FieldD>7A02</FieldD>
    <FieldE>Yatala Brewery</FieldE>
    <FieldF>0</FieldF>
    <FieldG>07.2019</FieldG>
  </Details>
  <Details>
    <FieldA>267247</FieldA>
    <FieldC>EA</FieldC>
    <FieldD>7A02</FieldD>
    <FieldE>Yatala Brewery</FieldE>
    <FieldF>24000</FieldF>
    <FieldG>08.2019</FieldG>
  </Details>
  <Details>
    <FieldA>267247</FieldA>
    <FieldC>EA</FieldC>
    <FieldD>7A02</FieldD>
    <FieldE>Yatala Brewery</FieldE>
    <FieldF>0</FieldF>
    <FieldG>09.2019</FieldG>
  </Details>
  <Details>
    <FieldA>267247</FieldA>
    <FieldC>EA</FieldC>
    <FieldD>7A02</FieldD>
    <FieldE>Yatala Brewery</FieldE>
    <FieldF>0</FieldF>
    <FieldG>10.2019</FieldG>
  </Details>
  <Details>
    <FieldA>267247</FieldA>
    <FieldC>EA</FieldC>
    <FieldD>7A02</FieldD>
    <FieldE>Yatala Brewery</FieldE>
    <FieldF>0</FieldF>
    <FieldG>11.2019</FieldG>
  </Details>
  <Details>
    <FieldA>267247</FieldA>
    <FieldC>EA</FieldC>
    <FieldD>7A02</FieldD>
    <FieldE>Yatala Brewery</FieldE>
    <FieldF>0</FieldF>
    <FieldG>12.2019</FieldG>
  </Details>
  <Details>
    <FieldA>267247</FieldA>
    <FieldC>EA</FieldC>
    <FieldD>7A02</FieldD>
    <FieldE>Yatala Brewery</FieldE>
    <FieldF>24000</FieldF>
    <FieldG>13.2019</FieldG>
  </Details>
  <Details>
    <FieldA>267247</FieldA>
    <FieldC>EA</FieldC>
    <FieldD>7A02</FieldD>
    <FieldE>Yatala Brewery</FieldE>
    <FieldF>0</FieldF>
    <FieldG>14.2019</FieldG>
  </Details>
  <Details>
    <FieldA>267247</FieldA>
    <FieldC>EA</FieldC>
    <FieldD>7A02</FieldD>
    <FieldE>Yatala Brewery</FieldE>
    <FieldF>0</FieldF>
    <FieldG>15.2019</FieldG>
  </Details>
  <Details>
    <FieldA>267247</FieldA>
    <FieldC>EA</FieldC>
    <FieldD>7A02</FieldD>
    <FieldE>Yatala Brewery</FieldE>
    <FieldF>0</FieldF>
    <FieldG>16.2019</FieldG>
  </Details>
  <Details>
    <FieldA>267247</FieldA>
    <FieldC>EA</FieldC>
    <FieldD>7A02</FieldD>
    <FieldE>Yatala Brewery</FieldE>
    <FieldF>24000</FieldF>
    <FieldG>17.2019</FieldG>
  </Details>
  <Details>
    <FieldA>267247</FieldA>
    <FieldC>EA</FieldC>
    <FieldD>7A02</FieldD>
    <FieldE>Yatala Brewery</FieldE>
    <FieldF>0</FieldF>
    <FieldG>18.2019</FieldG>
  </Details>
  <Details>
    <FieldA>267247</FieldA>
    <FieldC>EA</FieldC>
    <FieldD>7A02</FieldD>
    <FieldE>Yatala Brewery</FieldE>
    <FieldF>0</FieldF>
    <FieldG>19.2019</FieldG>
  </Details>
  <Details>
    <FieldA>267595</FieldA>
    <FieldC>EA</FieldC>
    <FieldD>7A02</FieldD>
    <FieldE>Yatala Brewery</FieldE>
    <FieldF>0</FieldF>
    <FieldG>06.2019</FieldG>
  </Details>
  <Details>
    <FieldA>267595</FieldA>
    <FieldC>EA</FieldC>
    <FieldD>7A02</FieldD>
    <FieldE>Yatala Brewery</FieldE>
    <FieldF>0</FieldF>
    <FieldG>07.2019</FieldG>
  </Details>
  <Details>
    <FieldA>267595</FieldA>
    <FieldC>EA</FieldC>
    <FieldD>7A02</FieldD>
    <FieldE>Yatala Brewery</FieldE>
    <FieldF>0</FieldF>
    <FieldG>08.2019</FieldG>
  </Details>
  <Details>
    <FieldA>267595</FieldA>
    <FieldC>EA</FieldC>
    <FieldD>7A02</FieldD>
    <FieldE>Yatala Brewery</FieldE>
    <FieldF>8064</FieldF>
    <FieldG>09.2019</FieldG>
  </Details>
  <Details>
    <FieldA>267595</FieldA>
    <FieldC>EA</FieldC>
    <FieldD>7A02</FieldD>
    <FieldE>Yatala Brewery</FieldE>
    <FieldF>0</FieldF>
    <FieldG>10.2019</FieldG>
  </Details>
  <Details>
    <FieldA>267595</FieldA>
    <FieldC>EA</FieldC>
    <FieldD>7A02</FieldD>
    <FieldE>Yatala Brewery</FieldE>
    <FieldF>0</FieldF>
    <FieldG>11.2019</FieldG>
  </Details>
  <Details>
    <FieldA>267595</FieldA>
    <FieldC>EA</FieldC>
    <FieldD>7A02</FieldD>
    <FieldE>Yatala Brewery</FieldE>
    <FieldF>0</FieldF>
    <FieldG>12.2019</FieldG>
  </Details>
  <Details>
    <FieldA>267595</FieldA>
    <FieldC>EA</FieldC>
    <FieldD>7A02</FieldD>
    <FieldE>Yatala Brewery</FieldE>
    <FieldF>20160</FieldF>
    <FieldG>13.2019</FieldG>
  </Details>
  <Details>
    <FieldA>267595</FieldA>
    <FieldC>EA</FieldC>
    <FieldD>7A02</FieldD>
    <FieldE>Yatala Brewery</FieldE>
    <FieldF>0</FieldF>
    <FieldG>14.2019</FieldG>
  </Details>
  <Details>
    <FieldA>267595</FieldA>
    <FieldC>EA</FieldC>
    <FieldD>7A02</FieldD>
    <FieldE>Yatala Brewery</FieldE>
    <FieldF>0</FieldF>
    <FieldG>15.2019</FieldG>
  </Details>
  <Details>
    <FieldA>267595</FieldA>
    <FieldC>EA</FieldC>
    <FieldD>7A02</FieldD>
    <FieldE>Yatala Brewery</FieldE>
    <FieldF>0</FieldF>
    <FieldG>16.2019</FieldG>
  </Details>
  <Details>
    <FieldA>267595</FieldA>
    <FieldC>EA</FieldC>
    <FieldD>7A02</FieldD>
    <FieldE>Yatala Brewery</FieldE>
    <FieldF>0</FieldF>
    <FieldG>17.2019</FieldG>
  </Details>
  <Details>
    <FieldA>267595</FieldA>
    <FieldC>EA</FieldC>
    <FieldD>7A02</FieldD>
    <FieldE>Yatala Brewery</FieldE>
    <FieldF>0</FieldF>
    <FieldG>18.2019</FieldG>
  </Details>
  <Details>
    <FieldA>267595</FieldA>
    <FieldC>EA</FieldC>
    <FieldD>7A02</FieldD>
    <FieldE>Yatala Brewery</FieldE>
    <FieldF>0</FieldF>
    <FieldG>19.2019</FieldG>
  </Details>
  <Details>
    <FieldA>269542</FieldA>
    <FieldC>EA</FieldC>
    <FieldD>7A02</FieldD>
    <FieldE>Yatala Brewery</FieldE>
    <FieldF>0</FieldF>
    <FieldG>06.2019</FieldG>
  </Details>
  <Details>
    <FieldA>269542</FieldA>
    <FieldC>EA</FieldC>
    <FieldD>7A02</FieldD>
    <FieldE>Yatala Brewery</FieldE>
    <FieldF>0</FieldF>
    <FieldG>07.2019</FieldG>
  </Details>
  <Details>
    <FieldA>269542</FieldA>
    <FieldC>EA</FieldC>
    <FieldD>7A02</FieldD>
    <FieldE>Yatala Brewery</FieldE>
    <FieldF>0</FieldF>
    <FieldG>08.2019</FieldG>
  </Details>
  <Details>
    <FieldA>269542</FieldA>
    <FieldC>EA</FieldC>
    <FieldD>7A02</FieldD>
    <FieldE>Yatala Brewery</FieldE>
    <FieldF>0</FieldF>
    <FieldG>09.2019</FieldG>
  </Details>
  <Details>
    <FieldA>269542</FieldA>
    <FieldC>EA</FieldC>
    <FieldD>7A02</FieldD>
    <FieldE>Yatala Brewery</FieldE>
    <FieldF>0</FieldF>
    <FieldG>10.2019</FieldG>
  </Details>
  <Details>
    <FieldA>269542</FieldA>
    <FieldC>EA</FieldC>
    <FieldD>7A02</FieldD>
    <FieldE>Yatala Brewery</FieldE>
    <FieldF>0</FieldF>
    <FieldG>11.2019</FieldG>
  </Details>
  <Details>
    <FieldA>269542</FieldA>
    <FieldC>EA</FieldC>
    <FieldD>7A02</FieldD>
    <FieldE>Yatala Brewery</FieldE>
    <FieldF>0</FieldF>
    <FieldG>12.2019</FieldG>
  </Details>
  <Details>
    <FieldA>269542</FieldA>
    <FieldC>EA</FieldC>
    <FieldD>7A02</FieldD>
    <FieldE>Yatala Brewery</FieldE>
    <FieldF>21000</FieldF>
    <FieldG>13.2019</FieldG>
  </Details>
  <Details>
    <FieldA>269542</FieldA>
    <FieldC>EA</FieldC>
    <FieldD>7A02</FieldD>
    <FieldE>Yatala Brewery</FieldE>
    <FieldF>0</FieldF>
    <FieldG>14.2019</FieldG>
  </Details>
  <Details>
    <FieldA>269542</FieldA>
    <FieldC>EA</FieldC>
    <FieldD>7A02</FieldD>
    <FieldE>Yatala Brewery</FieldE>
    <FieldF>0</FieldF>
    <FieldG>15.2019</FieldG>
  </Details>
  <Details>
    <FieldA>269542</FieldA>
    <FieldC>EA</FieldC>
    <FieldD>7A02</FieldD>
    <FieldE>Yatala Brewery</FieldE>
    <FieldF>0</FieldF>
    <FieldG>16.2019</FieldG>
  </Details>
  <Details>
    <FieldA>269542</FieldA>
    <FieldC>EA</FieldC>
    <FieldD>7A02</FieldD>
    <FieldE>Yatala Brewery</FieldE>
    <FieldF>0</FieldF>
    <FieldG>17.2019</FieldG>
  </Details>
  <Details>
    <FieldA>269542</FieldA>
    <FieldC>EA</FieldC>
    <FieldD>7A02</FieldD>
    <FieldE>Yatala Brewery</FieldE>
    <FieldF>0</FieldF>
    <FieldG>18.2019</FieldG>
  </Details>
  <Details>
    <FieldA>269542</FieldA>
    <FieldC>EA</FieldC>
    <FieldD>7A02</FieldD>
    <FieldE>Yatala Brewery</FieldE>
    <FieldF>0</FieldF>
    <FieldG>19.2019</FieldG>
  </Details>
  <Details>
    <FieldA>269744</FieldA>
    <FieldC>EA</FieldC>
    <FieldD>7A02</FieldD>
    <FieldE>Yatala Brewery</FieldE>
    <FieldF>0</FieldF>
    <FieldG>06.2019</FieldG>
  </Details>
  <Details>
    <FieldA>269744</FieldA>
    <FieldC>EA</FieldC>
    <FieldD>7A02</FieldD>
    <FieldE>Yatala Brewery</FieldE>
    <FieldF>0</FieldF>
    <FieldG>07.2019</FieldG>
  </Details>
  <Details>
    <FieldA>269744</FieldA>
    <FieldC>EA</FieldC>
    <FieldD>7A02</FieldD>
    <FieldE>Yatala Brewery</FieldE>
    <FieldF>0</FieldF>
    <FieldG>08.2019</FieldG>
  </Details>
  <Details>
    <FieldA>269744</FieldA>
    <FieldC>EA</FieldC>
    <FieldD>7A02</FieldD>
    <FieldE>Yatala Brewery</FieldE>
    <FieldF>169344</FieldF>
    <FieldG>09.2019</FieldG>
  </Details>
  <Details>
    <FieldA>269744</FieldA>
    <FieldC>EA</FieldC>
    <FieldD>7A02</FieldD>
    <FieldE>Yatala Brewery</FieldE>
    <FieldF>0</FieldF>
    <FieldG>10.2019</FieldG>
  </Details>
  <Details>
    <FieldA>269744</FieldA>
    <FieldC>EA</FieldC>
    <FieldD>7A02</FieldD>
    <FieldE>Yatala Brewery</FieldE>
    <FieldF>88704</FieldF>
    <FieldG>11.2019</FieldG>
  </Details>
  <Details>
    <FieldA>269744</FieldA>
    <FieldC>EA</FieldC>
    <FieldD>7A02</FieldD>
    <FieldE>Yatala Brewery</FieldE>
    <FieldF>0</FieldF>
    <FieldG>12.2019</FieldG>
  </Details>
  <Details>
    <FieldA>269744</FieldA>
    <FieldC>EA</FieldC>
    <FieldD>7A02</FieldD>
    <FieldE>Yatala Brewery</FieldE>
    <FieldF>0</FieldF>
    <FieldG>13.2019</FieldG>
  </Details>
  <Details>
    <FieldA>269744</FieldA>
    <FieldC>EA</FieldC>
    <FieldD>7A02</FieldD>
    <FieldE>Yatala Brewery</FieldE>
    <FieldF>0</FieldF>
    <FieldG>14.2019</FieldG>
  </Details>
  <Details>
    <FieldA>269744</FieldA>
    <FieldC>EA</FieldC>
    <FieldD>7A02</FieldD>
    <FieldE>Yatala Brewery</FieldE>
    <FieldF>80640</FieldF>
    <FieldG>15.2019</FieldG>
  </Details>
  <Details>
    <FieldA>269744</FieldA>
    <FieldC>EA</FieldC>
    <FieldD>7A02</FieldD>
    <FieldE>Yatala Brewery</FieldE>
    <FieldF>0</FieldF>
    <FieldG>16.2019</FieldG>
  </Details>
  <Details>
    <FieldA>269744</FieldA>
    <FieldC>EA</FieldC>
    <FieldD>7A02</FieldD>
    <FieldE>Yatala Brewery</FieldE>
    <FieldF>0</FieldF>
    <FieldG>17.2019</FieldG>
  </Details>
  <Details>
    <FieldA>269744</FieldA>
    <FieldC>EA</FieldC>
    <FieldD>7A02</FieldD>
    <FieldE>Yatala Brewery</FieldE>
    <FieldF>0</FieldF>
    <FieldG>18.2019</FieldG>
  </Details>
  <Details>
    <FieldA>269744</FieldA>
    <FieldC>EA</FieldC>
    <FieldD>7A02</FieldD>
    <FieldE>Yatala Brewery</FieldE>
    <FieldF>0</FieldF>
    <FieldG>19.2019</FieldG>
  </Details>
  <Details>
    <FieldA>270476</FieldA>
    <FieldC>EA</FieldC>
    <FieldD>7A01</FieldD>
    <FieldE>Abbotsford Brewery</FieldE>
    <FieldF>0</FieldF>
    <FieldG>06.2019</FieldG>
  </Details>
  <Details>
    <FieldA>270476</FieldA>
    <FieldC>EA</FieldC>
    <FieldD>7A01</FieldD>
    <FieldE>Abbotsford Brewery</FieldE>
    <FieldF>0</FieldF>
    <FieldG>07.2019</FieldG>
  </Details>
  <Details>
    <FieldA>270476</FieldA>
    <FieldC>EA</FieldC>
    <FieldD>7A01</FieldD>
    <FieldE>Abbotsford Brewery</FieldE>
    <FieldF>0</FieldF>
    <FieldG>08.2019</FieldG>
  </Details>
  <Details>
    <FieldA>270476</FieldA>
    <FieldC>EA</FieldC>
    <FieldD>7A01</FieldD>
    <FieldE>Abbotsford Brewery</FieldE>
    <FieldF>0</FieldF>
    <FieldG>09.2019</FieldG>
  </Details>
  <Details>
    <FieldA>270476</FieldA>
    <FieldC>EA</FieldC>
    <FieldD>7A01</FieldD>
    <FieldE>Abbotsford Brewery</FieldE>
    <FieldF>0</FieldF>
    <FieldG>10.2019</FieldG>
  </Details>
  <Details>
    <FieldA>270476</FieldA>
    <FieldC>EA</FieldC>
    <FieldD>7A01</FieldD>
    <FieldE>Abbotsford Brewery</FieldE>
    <FieldF>6048</FieldF>
    <FieldG>11.2019</FieldG>
  </Details>
  <Details>
    <FieldA>270476</FieldA>
    <FieldC>EA</FieldC>
    <FieldD>7A01</FieldD>
    <FieldE>Abbotsford Brewery</FieldE>
    <FieldF>0</FieldF>
    <FieldG>12.2019</FieldG>
  </Details>
  <Details>
    <FieldA>270476</FieldA>
    <FieldC>EA</FieldC>
    <FieldD>7A01</FieldD>
    <FieldE>Abbotsford Brewery</FieldE>
    <FieldF>18144</FieldF>
    <FieldG>13.2019</FieldG>
  </Details>
  <Details>
    <FieldA>270476</FieldA>
    <FieldC>EA</FieldC>
    <FieldD>7A01</FieldD>
    <FieldE>Abbotsford Brewery</FieldE>
    <FieldF>0</FieldF>
    <FieldG>14.2019</FieldG>
  </Details>
  <Details>
    <FieldA>270476</FieldA>
    <FieldC>EA</FieldC>
    <FieldD>7A01</FieldD>
    <FieldE>Abbotsford Brewery</FieldE>
    <FieldF>30240</FieldF>
    <FieldG>15.2019</FieldG>
  </Details>
  <Details>
    <FieldA>270476</FieldA>
    <FieldC>EA</FieldC>
    <FieldD>7A01</FieldD>
    <FieldE>Abbotsford Brewery</FieldE>
    <FieldF>0</FieldF>
    <FieldG>16.2019</FieldG>
  </Details>
  <Details>
    <FieldA>270476</FieldA>
    <FieldC>EA</FieldC>
    <FieldD>7A01</FieldD>
    <FieldE>Abbotsford Brewery</FieldE>
    <FieldF>0</FieldF>
    <FieldG>17.2019</FieldG>
  </Details>
  <Details>
    <FieldA>270476</FieldA>
    <FieldC>EA</FieldC>
    <FieldD>7A01</FieldD>
    <FieldE>Abbotsford Brewery</FieldE>
    <FieldF>0</FieldF>
    <FieldG>18.2019</FieldG>
  </Details>
  <Details>
    <FieldA>270476</FieldA>
    <FieldC>EA</FieldC>
    <FieldD>7A01</FieldD>
    <FieldE>Abbotsford Brewery</FieldE>
    <FieldF>0</FieldF>
    <FieldG>19.2019</FieldG>
  </Details>
  <Details>
    <FieldA>270476</FieldA>
    <FieldC>EA</FieldC>
    <FieldD>7A02</FieldD>
    <FieldE>Yatala Brewery</FieldE>
    <FieldF>0</FieldF>
    <FieldG>06.2019</FieldG>
  </Details>
  <Details>
    <FieldA>270476</FieldA>
    <FieldC>EA</FieldC>
    <FieldD>7A02</FieldD>
    <FieldE>Yatala Brewery</FieldE>
    <FieldF>0</FieldF>
    <FieldG>07.2019</FieldG>
  </Details>
  <Details>
    <FieldA>270476</FieldA>
    <FieldC>EA</FieldC>
    <FieldD>7A02</FieldD>
    <FieldE>Yatala Brewery</FieldE>
    <FieldF>0</FieldF>
    <FieldG>08.2019</FieldG>
  </Details>
  <Details>
    <FieldA>270476</FieldA>
    <FieldC>EA</FieldC>
    <FieldD>7A02</FieldD>
    <FieldE>Yatala Brewery</FieldE>
    <FieldF>0</FieldF>
    <FieldG>09.2019</FieldG>
  </Details>
  <Details>
    <FieldA>270476</FieldA>
    <FieldC>EA</FieldC>
    <FieldD>7A02</FieldD>
    <FieldE>Yatala Brewery</FieldE>
    <FieldF>0</FieldF>
    <FieldG>10.2019</FieldG>
  </Details>
  <Details>
    <FieldA>270476</FieldA>
    <FieldC>EA</FieldC>
    <FieldD>7A02</FieldD>
    <FieldE>Yatala Brewery</FieldE>
    <FieldF>0</FieldF>
    <FieldG>11.2019</FieldG>
  </Details>
  <Details>
    <FieldA>270476</FieldA>
    <FieldC>EA</FieldC>
    <FieldD>7A02</FieldD>
    <FieldE>Yatala Brewery</FieldE>
    <FieldF>36288</FieldF>
    <FieldG>12.2019</FieldG>
  </Details>
  <Details>
    <FieldA>270476</FieldA>
    <FieldC>EA</FieldC>
    <FieldD>7A02</FieldD>
    <FieldE>Yatala Brewery</FieldE>
    <FieldF>0</FieldF>
    <FieldG>13.2019</FieldG>
  </Details>
  <Details>
    <FieldA>270476</FieldA>
    <FieldC>EA</FieldC>
    <FieldD>7A02</FieldD>
    <FieldE>Yatala Brewery</FieldE>
    <FieldF>40320</FieldF>
    <FieldG>14.2019</FieldG>
  </Details>
  <Details>
    <FieldA>270476</FieldA>
    <FieldC>EA</FieldC>
    <FieldD>7A02</FieldD>
    <FieldE>Yatala Brewery</FieldE>
    <FieldF>0</FieldF>
    <FieldG>15.2019</FieldG>
  </Details>
  <Details>
    <FieldA>270476</FieldA>
    <FieldC>EA</FieldC>
    <FieldD>7A02</FieldD>
    <FieldE>Yatala Brewery</FieldE>
    <FieldF>40320</FieldF>
    <FieldG>16.2019</FieldG>
  </Details>
  <Details>
    <FieldA>270476</FieldA>
    <FieldC>EA</FieldC>
    <FieldD>7A02</FieldD>
    <FieldE>Yatala Brewery</FieldE>
    <FieldF>0</FieldF>
    <FieldG>17.2019</FieldG>
  </Details>
  <Details>
    <FieldA>270476</FieldA>
    <FieldC>EA</FieldC>
    <FieldD>7A02</FieldD>
    <FieldE>Yatala Brewery</FieldE>
    <FieldF>40320</FieldF>
    <FieldG>18.2019</FieldG>
  </Details>
  <Details>
    <FieldA>270476</FieldA>
    <FieldC>EA</FieldC>
    <FieldD>7A02</FieldD>
    <FieldE>Yatala Brewery</FieldE>
    <FieldF>0</FieldF>
    <FieldG>19.2019</FieldG>
  </Details>
  <Details>
    <FieldA>273529</FieldA>
    <FieldC>EA</FieldC>
    <FieldD>7A02</FieldD>
    <FieldE>Yatala Brewery</FieldE>
    <FieldF>0</FieldF>
    <FieldG>06.2019</FieldG>
  </Details>
  <Details>
    <FieldA>273529</FieldA>
    <FieldC>EA</FieldC>
    <FieldD>7A02</FieldD>
    <FieldE>Yatala Brewery</FieldE>
    <FieldF>0</FieldF>
    <FieldG>07.2019</FieldG>
  </Details>
  <Details>
    <FieldA>273529</FieldA>
    <FieldC>EA</FieldC>
    <FieldD>7A02</FieldD>
    <FieldE>Yatala Brewery</FieldE>
    <FieldF>0</FieldF>
    <FieldG>08.2019</FieldG>
  </Details>
  <Details>
    <FieldA>273529</FieldA>
    <FieldC>EA</FieldC>
    <FieldD>7A02</FieldD>
    <FieldE>Yatala Brewery</FieldE>
    <FieldF>0</FieldF>
    <FieldG>09.2019</FieldG>
  </Details>
  <Details>
    <FieldA>273529</FieldA>
    <FieldC>EA</FieldC>
    <FieldD>7A02</FieldD>
    <FieldE>Yatala Brewery</FieldE>
    <FieldF>0</FieldF>
    <FieldG>10.2019</FieldG>
  </Details>
  <Details>
    <FieldA>273529</FieldA>
    <FieldC>EA</FieldC>
    <FieldD>7A02</FieldD>
    <FieldE>Yatala Brewery</FieldE>
    <FieldF>0</FieldF>
    <FieldG>11.2019</FieldG>
  </Details>
  <Details>
    <FieldA>273529</FieldA>
    <FieldC>EA</FieldC>
    <FieldD>7A02</FieldD>
    <FieldE>Yatala Brewery</FieldE>
    <FieldF>24000</FieldF>
    <FieldG>12.2019</FieldG>
  </Details>
  <Details>
    <FieldA>273529</FieldA>
    <FieldC>EA</FieldC>
    <FieldD>7A02</FieldD>
    <FieldE>Yatala Brewery</FieldE>
    <FieldF>0</FieldF>
    <FieldG>13.2019</FieldG>
  </Details>
  <Details>
    <FieldA>273529</FieldA>
    <FieldC>EA</FieldC>
    <FieldD>7A02</FieldD>
    <FieldE>Yatala Brewery</FieldE>
    <FieldF>0</FieldF>
    <FieldG>14.2019</FieldG>
  </Details>
  <Details>
    <FieldA>273529</FieldA>
    <FieldC>EA</FieldC>
    <FieldD>7A02</FieldD>
    <FieldE>Yatala Brewery</FieldE>
    <FieldF>0</FieldF>
    <FieldG>15.2019</FieldG>
  </Details>
  <Details>
    <FieldA>273529</FieldA>
    <FieldC>EA</FieldC>
    <FieldD>7A02</FieldD>
    <FieldE>Yatala Brewery</FieldE>
    <FieldF>15000</FieldF>
    <FieldG>16.2019</FieldG>
  </Details>
  <Details>
    <FieldA>273529</FieldA>
    <FieldC>EA</FieldC>
    <FieldD>7A02</FieldD>
    <FieldE>Yatala Brewery</FieldE>
    <FieldF>0</FieldF>
    <FieldG>17.2019</FieldG>
  </Details>
  <Details>
    <FieldA>273529</FieldA>
    <FieldC>EA</FieldC>
    <FieldD>7A02</FieldD>
    <FieldE>Yatala Brewery</FieldE>
    <FieldF>0</FieldF>
    <FieldG>18.2019</FieldG>
  </Details>
  <Details>
    <FieldA>273529</FieldA>
    <FieldC>EA</FieldC>
    <FieldD>7A02</FieldD>
    <FieldE>Yatala Brewery</FieldE>
    <FieldF>0</FieldF>
    <FieldG>19.2019</FieldG>
  </Details>
  <Details>
    <FieldA>273549</FieldA>
    <FieldC>EA</FieldC>
    <FieldD>7A02</FieldD>
    <FieldE>Yatala Brewery</FieldE>
    <FieldF>0</FieldF>
    <FieldG>06.2019</FieldG>
  </Details>
  <Details>
    <FieldA>273549</FieldA>
    <FieldC>EA</FieldC>
    <FieldD>7A02</FieldD>
    <FieldE>Yatala Brewery</FieldE>
    <FieldF>0</FieldF>
    <FieldG>07.2019</FieldG>
  </Details>
  <Details>
    <FieldA>273549</FieldA>
    <FieldC>EA</FieldC>
    <FieldD>7A02</FieldD>
    <FieldE>Yatala Brewery</FieldE>
    <FieldF>0</FieldF>
    <FieldG>08.2019</FieldG>
  </Details>
  <Details>
    <FieldA>273549</FieldA>
    <FieldC>EA</FieldC>
    <FieldD>7A02</FieldD>
    <FieldE>Yatala Brewery</FieldE>
    <FieldF>0</FieldF>
    <FieldG>09.2019</FieldG>
  </Details>
  <Details>
    <FieldA>273549</FieldA>
    <FieldC>EA</FieldC>
    <FieldD>7A02</FieldD>
    <FieldE>Yatala Brewery</FieldE>
    <FieldF>0</FieldF>
    <FieldG>10.2019</FieldG>
  </Details>
  <Details>
    <FieldA>273549</FieldA>
    <FieldC>EA</FieldC>
    <FieldD>7A02</FieldD>
    <FieldE>Yatala Brewery</FieldE>
    <FieldF>0</FieldF>
    <FieldG>11.2019</FieldG>
  </Details>
  <Details>
    <FieldA>273549</FieldA>
    <FieldC>EA</FieldC>
    <FieldD>7A02</FieldD>
    <FieldE>Yatala Brewery</FieldE>
    <FieldF>0</FieldF>
    <FieldG>12.2019</FieldG>
  </Details>
  <Details>
    <FieldA>273549</FieldA>
    <FieldC>EA</FieldC>
    <FieldD>7A02</FieldD>
    <FieldE>Yatala Brewery</FieldE>
    <FieldF>0</FieldF>
    <FieldG>13.2019</FieldG>
  </Details>
  <Details>
    <FieldA>273549</FieldA>
    <FieldC>EA</FieldC>
    <FieldD>7A02</FieldD>
    <FieldE>Yatala Brewery</FieldE>
    <FieldF>0</FieldF>
    <FieldG>14.2019</FieldG>
  </Details>
  <Details>
    <FieldA>273549</FieldA>
    <FieldC>EA</FieldC>
    <FieldD>7A02</FieldD>
    <FieldE>Yatala Brewery</FieldE>
    <FieldF>0</FieldF>
    <FieldG>15.2019</FieldG>
  </Details>
  <Details>
    <FieldA>273549</FieldA>
    <FieldC>EA</FieldC>
    <FieldD>7A02</FieldD>
    <FieldE>Yatala Brewery</FieldE>
    <FieldF>15000</FieldF>
    <FieldG>16.2019</FieldG>
  </Details>
  <Details>
    <FieldA>273549</FieldA>
    <FieldC>EA</FieldC>
    <FieldD>7A02</FieldD>
    <FieldE>Yatala Brewery</FieldE>
    <FieldF>0</FieldF>
    <FieldG>17.2019</FieldG>
  </Details>
  <Details>
    <FieldA>273549</FieldA>
    <FieldC>EA</FieldC>
    <FieldD>7A02</FieldD>
    <FieldE>Yatala Brewery</FieldE>
    <FieldF>0</FieldF>
    <FieldG>18.2019</FieldG>
  </Details>
  <Details>
    <FieldA>273549</FieldA>
    <FieldC>EA</FieldC>
    <FieldD>7A02</FieldD>
    <FieldE>Yatala Brewery</FieldE>
    <FieldF>0</FieldF>
    <FieldG>19.2019</FieldG>
  </Details>
  <Details>
    <FieldA>274138</FieldA>
    <FieldC>EA</FieldC>
    <FieldD>7A01</FieldD>
    <FieldE>Abbotsford Brewery</FieldE>
    <FieldF>0</FieldF>
    <FieldG>06.2019</FieldG>
  </Details>
  <Details>
    <FieldA>274138</FieldA>
    <FieldC>EA</FieldC>
    <FieldD>7A01</FieldD>
    <FieldE>Abbotsford Brewery</FieldE>
    <FieldF>0</FieldF>
    <FieldG>07.2019</FieldG>
  </Details>
  <Details>
    <FieldA>274138</FieldA>
    <FieldC>EA</FieldC>
    <FieldD>7A01</FieldD>
    <FieldE>Abbotsford Brewery</FieldE>
    <FieldF>0</FieldF>
    <FieldG>08.2019</FieldG>
  </Details>
  <Details>
    <FieldA>274138</FieldA>
    <FieldC>EA</FieldC>
    <FieldD>7A01</FieldD>
    <FieldE>Abbotsford Brewery</FieldE>
    <FieldF>0</FieldF>
    <FieldG>09.2019</FieldG>
  </Details>
  <Details>
    <FieldA>274138</FieldA>
    <FieldC>EA</FieldC>
    <FieldD>7A01</FieldD>
    <FieldE>Abbotsford Brewery</FieldE>
    <FieldF>0</FieldF>
    <FieldG>10.2019</FieldG>
  </Details>
  <Details>
    <FieldA>274138</FieldA>
    <FieldC>EA</FieldC>
    <FieldD>7A01</FieldD>
    <FieldE>Abbotsford Brewery</FieldE>
    <FieldF>0</FieldF>
    <FieldG>11.2019</FieldG>
  </Details>
  <Details>
    <FieldA>274138</FieldA>
    <FieldC>EA</FieldC>
    <FieldD>7A01</FieldD>
    <FieldE>Abbotsford Brewery</FieldE>
    <FieldF>10080</FieldF>
    <FieldG>12.2019</FieldG>
  </Details>
  <Details>
    <FieldA>274138</FieldA>
    <FieldC>EA</FieldC>
    <FieldD>7A01</FieldD>
    <FieldE>Abbotsford Brewery</FieldE>
    <FieldF>20160</FieldF>
    <FieldG>13.2019</FieldG>
  </Details>
  <Details>
    <FieldA>274138</FieldA>
    <FieldC>EA</FieldC>
    <FieldD>7A01</FieldD>
    <FieldE>Abbotsford Brewery</FieldE>
    <FieldF>0</FieldF>
    <FieldG>14.2019</FieldG>
  </Details>
  <Details>
    <FieldA>274138</FieldA>
    <FieldC>EA</FieldC>
    <FieldD>7A01</FieldD>
    <FieldE>Abbotsford Brewery</FieldE>
    <FieldF>20160</FieldF>
    <FieldG>15.2019</FieldG>
  </Details>
  <Details>
    <FieldA>274138</FieldA>
    <FieldC>EA</FieldC>
    <FieldD>7A01</FieldD>
    <FieldE>Abbotsford Brewery</FieldE>
    <FieldF>0</FieldF>
    <FieldG>16.2019</FieldG>
  </Details>
  <Details>
    <FieldA>274138</FieldA>
    <FieldC>EA</FieldC>
    <FieldD>7A01</FieldD>
    <FieldE>Abbotsford Brewery</FieldE>
    <FieldF>0</FieldF>
    <FieldG>17.2019</FieldG>
  </Details>
  <Details>
    <FieldA>274138</FieldA>
    <FieldC>EA</FieldC>
    <FieldD>7A01</FieldD>
    <FieldE>Abbotsford Brewery</FieldE>
    <FieldF>20160</FieldF>
    <FieldG>18.2019</FieldG>
  </Details>
  <Details>
    <FieldA>274138</FieldA>
    <FieldC>EA</FieldC>
    <FieldD>7A01</FieldD>
    <FieldE>Abbotsford Brewery</FieldE>
    <FieldF>0</FieldF>
    <FieldG>19.2019</FieldG>
  </Details>
  <Details>
    <FieldA>274138</FieldA>
    <FieldC>EA</FieldC>
    <FieldD>7A02</FieldD>
    <FieldE>Yatala Brewery</FieldE>
    <FieldF>0</FieldF>
    <FieldG>06.2019</FieldG>
  </Details>
  <Details>
    <FieldA>274138</FieldA>
    <FieldC>EA</FieldC>
    <FieldD>7A02</FieldD>
    <FieldE>Yatala Brewery</FieldE>
    <FieldF>0</FieldF>
    <FieldG>07.2019</FieldG>
  </Details>
  <Details>
    <FieldA>274138</FieldA>
    <FieldC>EA</FieldC>
    <FieldD>7A02</FieldD>
    <FieldE>Yatala Brewery</FieldE>
    <FieldF>0</FieldF>
    <FieldG>08.2019</FieldG>
  </Details>
  <Details>
    <FieldA>274138</FieldA>
    <FieldC>EA</FieldC>
    <FieldD>7A02</FieldD>
    <FieldE>Yatala Brewery</FieldE>
    <FieldF>30240</FieldF>
    <FieldG>09.2019</FieldG>
  </Details>
  <Details>
    <FieldA>274138</FieldA>
    <FieldC>EA</FieldC>
    <FieldD>7A02</FieldD>
    <FieldE>Yatala Brewery</FieldE>
    <FieldF>0</FieldF>
    <FieldG>10.2019</FieldG>
  </Details>
  <Details>
    <FieldA>274138</FieldA>
    <FieldC>EA</FieldC>
    <FieldD>7A02</FieldD>
    <FieldE>Yatala Brewery</FieldE>
    <FieldF>0</FieldF>
    <FieldG>11.2019</FieldG>
  </Details>
  <Details>
    <FieldA>274138</FieldA>
    <FieldC>EA</FieldC>
    <FieldD>7A02</FieldD>
    <FieldE>Yatala Brewery</FieldE>
    <FieldF>80640</FieldF>
    <FieldG>12.2019</FieldG>
  </Details>
  <Details>
    <FieldA>274138</FieldA>
    <FieldC>EA</FieldC>
    <FieldD>7A02</FieldD>
    <FieldE>Yatala Brewery</FieldE>
    <FieldF>0</FieldF>
    <FieldG>13.2019</FieldG>
  </Details>
  <Details>
    <FieldA>274138</FieldA>
    <FieldC>EA</FieldC>
    <FieldD>7A02</FieldD>
    <FieldE>Yatala Brewery</FieldE>
    <FieldF>102816</FieldF>
    <FieldG>14.2019</FieldG>
  </Details>
  <Details>
    <FieldA>274138</FieldA>
    <FieldC>EA</FieldC>
    <FieldD>7A02</FieldD>
    <FieldE>Yatala Brewery</FieldE>
    <FieldF>0</FieldF>
    <FieldG>15.2019</FieldG>
  </Details>
  <Details>
    <FieldA>274138</FieldA>
    <FieldC>EA</FieldC>
    <FieldD>7A02</FieldD>
    <FieldE>Yatala Brewery</FieldE>
    <FieldF>58464</FieldF>
    <FieldG>16.2019</FieldG>
  </Details>
  <Details>
    <FieldA>274138</FieldA>
    <FieldC>EA</FieldC>
    <FieldD>7A02</FieldD>
    <FieldE>Yatala Brewery</FieldE>
    <FieldF>0</FieldF>
    <FieldG>17.2019</FieldG>
  </Details>
  <Details>
    <FieldA>274138</FieldA>
    <FieldC>EA</FieldC>
    <FieldD>7A02</FieldD>
    <FieldE>Yatala Brewery</FieldE>
    <FieldF>80640</FieldF>
    <FieldG>18.2019</FieldG>
  </Details>
  <Details>
    <FieldA>274138</FieldA>
    <FieldC>EA</FieldC>
    <FieldD>7A02</FieldD>
    <FieldE>Yatala Brewery</FieldE>
    <FieldF>0</FieldF>
    <FieldG>19.2019</FieldG>
  </Details>
  <Details>
    <FieldA>274663</FieldA>
    <FieldC>EA</FieldC>
    <FieldD>7A01</FieldD>
    <FieldE>Abbotsford Brewery</FieldE>
    <FieldF>0</FieldF>
    <FieldG>06.2019</FieldG>
  </Details>
  <Details>
    <FieldA>274663</FieldA>
    <FieldC>EA</FieldC>
    <FieldD>7A01</FieldD>
    <FieldE>Abbotsford Brewery</FieldE>
    <FieldF>0</FieldF>
    <FieldG>07.2019</FieldG>
  </Details>
  <Details>
    <FieldA>274663</FieldA>
    <FieldC>EA</FieldC>
    <FieldD>7A01</FieldD>
    <FieldE>Abbotsford Brewery</FieldE>
    <FieldF>0</FieldF>
    <FieldG>08.2019</FieldG>
  </Details>
  <Details>
    <FieldA>274663</FieldA>
    <FieldC>EA</FieldC>
    <FieldD>7A01</FieldD>
    <FieldE>Abbotsford Brewery</FieldE>
    <FieldF>0</FieldF>
    <FieldG>09.2019</FieldG>
  </Details>
  <Details>
    <FieldA>274663</FieldA>
    <FieldC>EA</FieldC>
    <FieldD>7A01</FieldD>
    <FieldE>Abbotsford Brewery</FieldE>
    <FieldF>0</FieldF>
    <FieldG>10.2019</FieldG>
  </Details>
  <Details>
    <FieldA>274663</FieldA>
    <FieldC>EA</FieldC>
    <FieldD>7A01</FieldD>
    <FieldE>Abbotsford Brewery</FieldE>
    <FieldF>0</FieldF>
    <FieldG>11.2019</FieldG>
  </Details>
  <Details>
    <FieldA>274663</FieldA>
    <FieldC>EA</FieldC>
    <FieldD>7A01</FieldD>
    <FieldE>Abbotsford Brewery</FieldE>
    <FieldF>0</FieldF>
    <FieldG>12.2019</FieldG>
  </Details>
  <Details>
    <FieldA>274663</FieldA>
    <FieldC>EA</FieldC>
    <FieldD>7A01</FieldD>
    <FieldE>Abbotsford Brewery</FieldE>
    <FieldF>0</FieldF>
    <FieldG>13.2019</FieldG>
  </Details>
  <Details>
    <FieldA>274663</FieldA>
    <FieldC>EA</FieldC>
    <FieldD>7A01</FieldD>
    <FieldE>Abbotsford Brewery</FieldE>
    <FieldF>30240</FieldF>
    <FieldG>14.2019</FieldG>
  </Details>
  <Details>
    <FieldA>274663</FieldA>
    <FieldC>EA</FieldC>
    <FieldD>7A01</FieldD>
    <FieldE>Abbotsford Brewery</FieldE>
    <FieldF>0</FieldF>
    <FieldG>15.2019</FieldG>
  </Details>
  <Details>
    <FieldA>274663</FieldA>
    <FieldC>EA</FieldC>
    <FieldD>7A01</FieldD>
    <FieldE>Abbotsford Brewery</FieldE>
    <FieldF>30240</FieldF>
    <FieldG>16.2019</FieldG>
  </Details>
  <Details>
    <FieldA>274663</FieldA>
    <FieldC>EA</FieldC>
    <FieldD>7A01</FieldD>
    <FieldE>Abbotsford Brewery</FieldE>
    <FieldF>30240</FieldF>
    <FieldG>17.2019</FieldG>
  </Details>
  <Details>
    <FieldA>274663</FieldA>
    <FieldC>EA</FieldC>
    <FieldD>7A01</FieldD>
    <FieldE>Abbotsford Brewery</FieldE>
    <FieldF>50400</FieldF>
    <FieldG>18.2019</FieldG>
  </Details>
  <Details>
    <FieldA>274663</FieldA>
    <FieldC>EA</FieldC>
    <FieldD>7A01</FieldD>
    <FieldE>Abbotsford Brewery</FieldE>
    <FieldF>0</FieldF>
    <FieldG>19.2019</FieldG>
  </Details>
  <Details>
    <FieldA>275685</FieldA>
    <FieldC>EA</FieldC>
    <FieldD>7A02</FieldD>
    <FieldE>Yatala Brewery</FieldE>
    <FieldF>0</FieldF>
    <FieldG>06.2019</FieldG>
  </Details>
  <Details>
    <FieldA>275685</FieldA>
    <FieldC>EA</FieldC>
    <FieldD>7A02</FieldD>
    <FieldE>Yatala Brewery</FieldE>
    <FieldF>0</FieldF>
    <FieldG>07.2019</FieldG>
  </Details>
  <Details>
    <FieldA>275685</FieldA>
    <FieldC>EA</FieldC>
    <FieldD>7A02</FieldD>
    <FieldE>Yatala Brewery</FieldE>
    <FieldF>0</FieldF>
    <FieldG>08.2019</FieldG>
  </Details>
  <Details>
    <FieldA>275685</FieldA>
    <FieldC>EA</FieldC>
    <FieldD>7A02</FieldD>
    <FieldE>Yatala Brewery</FieldE>
    <FieldF>0</FieldF>
    <FieldG>09.2019</FieldG>
  </Details>
  <Details>
    <FieldA>275685</FieldA>
    <FieldC>EA</FieldC>
    <FieldD>7A02</FieldD>
    <FieldE>Yatala Brewery</FieldE>
    <FieldF>0</FieldF>
    <FieldG>10.2019</FieldG>
  </Details>
  <Details>
    <FieldA>275685</FieldA>
    <FieldC>EA</FieldC>
    <FieldD>7A02</FieldD>
    <FieldE>Yatala Brewery</FieldE>
    <FieldF>72576</FieldF>
    <FieldG>11.2019</FieldG>
  </Details>
  <Details>
    <FieldA>275685</FieldA>
    <FieldC>EA</FieldC>
    <FieldD>7A02</FieldD>
    <FieldE>Yatala Brewery</FieldE>
    <FieldF>66528</FieldF>
    <FieldG>12.2019</FieldG>
  </Details>
  <Details>
    <FieldA>275685</FieldA>
    <FieldC>EA</FieldC>
    <FieldD>7A02</FieldD>
    <FieldE>Yatala Brewery</FieldE>
    <FieldF>58464</FieldF>
    <FieldG>13.2019</FieldG>
  </Details>
  <Details>
    <FieldA>275685</FieldA>
    <FieldC>EA</FieldC>
    <FieldD>7A02</FieldD>
    <FieldE>Yatala Brewery</FieldE>
    <FieldF>86688</FieldF>
    <FieldG>14.2019</FieldG>
  </Details>
  <Details>
    <FieldA>275685</FieldA>
    <FieldC>EA</FieldC>
    <FieldD>7A02</FieldD>
    <FieldE>Yatala Brewery</FieldE>
    <FieldF>20160</FieldF>
    <FieldG>15.2019</FieldG>
  </Details>
  <Details>
    <FieldA>275685</FieldA>
    <FieldC>EA</FieldC>
    <FieldD>7A02</FieldD>
    <FieldE>Yatala Brewery</FieldE>
    <FieldF>20160</FieldF>
    <FieldG>16.2019</FieldG>
  </Details>
  <Details>
    <FieldA>275685</FieldA>
    <FieldC>EA</FieldC>
    <FieldD>7A02</FieldD>
    <FieldE>Yatala Brewery</FieldE>
    <FieldF>0</FieldF>
    <FieldG>17.2019</FieldG>
  </Details>
  <Details>
    <FieldA>275685</FieldA>
    <FieldC>EA</FieldC>
    <FieldD>7A02</FieldD>
    <FieldE>Yatala Brewery</FieldE>
    <FieldF>0</FieldF>
    <FieldG>18.2019</FieldG>
  </Details>
  <Details>
    <FieldA>275685</FieldA>
    <FieldC>EA</FieldC>
    <FieldD>7A02</FieldD>
    <FieldE>Yatala Brewery</FieldE>
    <FieldF>0</FieldF>
    <FieldG>19.2019</FieldG>
  </Details>
  <Details>
    <FieldA>275686</FieldA>
    <FieldC>EA</FieldC>
    <FieldD>7A01</FieldD>
    <FieldE>Abbotsford Brewery</FieldE>
    <FieldF>0</FieldF>
    <FieldG>06.2019</FieldG>
  </Details>
  <Details>
    <FieldA>275686</FieldA>
    <FieldC>EA</FieldC>
    <FieldD>7A01</FieldD>
    <FieldE>Abbotsford Brewery</FieldE>
    <FieldF>12100</FieldF>
    <FieldG>07.2019</FieldG>
  </Details>
  <Details>
    <FieldA>275686</FieldA>
    <FieldC>EA</FieldC>
    <FieldD>7A01</FieldD>
    <FieldE>Abbotsford Brewery</FieldE>
    <FieldF>0</FieldF>
    <FieldG>08.2019</FieldG>
  </Details>
  <Details>
    <FieldA>275686</FieldA>
    <FieldC>EA</FieldC>
    <FieldD>7A01</FieldD>
    <FieldE>Abbotsford Brewery</FieldE>
    <FieldF>14400</FieldF>
    <FieldG>09.2019</FieldG>
  </Details>
  <Details>
    <FieldA>275686</FieldA>
    <FieldC>EA</FieldC>
    <FieldD>7A01</FieldD>
    <FieldE>Abbotsford Brewery</FieldE>
    <FieldF>0</FieldF>
    <FieldG>10.2019</FieldG>
  </Details>
  <Details>
    <FieldA>275686</FieldA>
    <FieldC>EA</FieldC>
    <FieldD>7A01</FieldD>
    <FieldE>Abbotsford Brewery</FieldE>
    <FieldF>44400</FieldF>
    <FieldG>11.2019</FieldG>
  </Details>
  <Details>
    <FieldA>275686</FieldA>
    <FieldC>EA</FieldC>
    <FieldD>7A01</FieldD>
    <FieldE>Abbotsford Brewery</FieldE>
    <FieldF>60000</FieldF>
    <FieldG>12.2019</FieldG>
  </Details>
  <Details>
    <FieldA>275686</FieldA>
    <FieldC>EA</FieldC>
    <FieldD>7A01</FieldD>
    <FieldE>Abbotsford Brewery</FieldE>
    <FieldF>33600</FieldF>
    <FieldG>13.2019</FieldG>
  </Details>
  <Details>
    <FieldA>275686</FieldA>
    <FieldC>EA</FieldC>
    <FieldD>7A01</FieldD>
    <FieldE>Abbotsford Brewery</FieldE>
    <FieldF>82800</FieldF>
    <FieldG>14.2019</FieldG>
  </Details>
  <Details>
    <FieldA>275686</FieldA>
    <FieldC>EA</FieldC>
    <FieldD>7A01</FieldD>
    <FieldE>Abbotsford Brewery</FieldE>
    <FieldF>0</FieldF>
    <FieldG>15.2019</FieldG>
  </Details>
  <Details>
    <FieldA>275686</FieldA>
    <FieldC>EA</FieldC>
    <FieldD>7A01</FieldD>
    <FieldE>Abbotsford Brewery</FieldE>
    <FieldF>0</FieldF>
    <FieldG>16.2019</FieldG>
  </Details>
  <Details>
    <FieldA>275686</FieldA>
    <FieldC>EA</FieldC>
    <FieldD>7A01</FieldD>
    <FieldE>Abbotsford Brewery</FieldE>
    <FieldF>0</FieldF>
    <FieldG>17.2019</FieldG>
  </Details>
  <Details>
    <FieldA>275686</FieldA>
    <FieldC>EA</FieldC>
    <FieldD>7A01</FieldD>
    <FieldE>Abbotsford Brewery</FieldE>
    <FieldF>0</FieldF>
    <FieldG>18.2019</FieldG>
  </Details>
  <Details>
    <FieldA>275686</FieldA>
    <FieldC>EA</FieldC>
    <FieldD>7A01</FieldD>
    <FieldE>Abbotsford Brewery</FieldE>
    <FieldF>0</FieldF>
    <FieldG>19.2019</FieldG>
  </Details>
  <Details>
    <FieldA>275689</FieldA>
    <FieldC>EA</FieldC>
    <FieldD>7A02</FieldD>
    <FieldE>Yatala Brewery</FieldE>
    <FieldF>0</FieldF>
    <FieldG>06.2019</FieldG>
  </Details>
  <Details>
    <FieldA>275689</FieldA>
    <FieldC>EA</FieldC>
    <FieldD>7A02</FieldD>
    <FieldE>Yatala Brewery</FieldE>
    <FieldF>0</FieldF>
    <FieldG>07.2019</FieldG>
  </Details>
  <Details>
    <FieldA>275689</FieldA>
    <FieldC>EA</FieldC>
    <FieldD>7A02</FieldD>
    <FieldE>Yatala Brewery</FieldE>
    <FieldF>0</FieldF>
    <FieldG>08.2019</FieldG>
  </Details>
  <Details>
    <FieldA>275689</FieldA>
    <FieldC>EA</FieldC>
    <FieldD>7A02</FieldD>
    <FieldE>Yatala Brewery</FieldE>
    <FieldF>0</FieldF>
    <FieldG>09.2019</FieldG>
  </Details>
  <Details>
    <FieldA>275689</FieldA>
    <FieldC>EA</FieldC>
    <FieldD>7A02</FieldD>
    <FieldE>Yatala Brewery</FieldE>
    <FieldF>0</FieldF>
    <FieldG>10.2019</FieldG>
  </Details>
  <Details>
    <FieldA>275689</FieldA>
    <FieldC>EA</FieldC>
    <FieldD>7A02</FieldD>
    <FieldE>Yatala Brewery</FieldE>
    <FieldF>76608</FieldF>
    <FieldG>11.2019</FieldG>
  </Details>
  <Details>
    <FieldA>275689</FieldA>
    <FieldC>EA</FieldC>
    <FieldD>7A02</FieldD>
    <FieldE>Yatala Brewery</FieldE>
    <FieldF>0</FieldF>
    <FieldG>12.2019</FieldG>
  </Details>
  <Details>
    <FieldA>275689</FieldA>
    <FieldC>EA</FieldC>
    <FieldD>7A02</FieldD>
    <FieldE>Yatala Brewery</FieldE>
    <FieldF>40320</FieldF>
    <FieldG>13.2019</FieldG>
  </Details>
  <Details>
    <FieldA>275689</FieldA>
    <FieldC>EA</FieldC>
    <FieldD>7A02</FieldD>
    <FieldE>Yatala Brewery</FieldE>
    <FieldF>0</FieldF>
    <FieldG>14.2019</FieldG>
  </Details>
  <Details>
    <FieldA>275689</FieldA>
    <FieldC>EA</FieldC>
    <FieldD>7A02</FieldD>
    <FieldE>Yatala Brewery</FieldE>
    <FieldF>34272</FieldF>
    <FieldG>15.2019</FieldG>
  </Details>
  <Details>
    <FieldA>275689</FieldA>
    <FieldC>EA</FieldC>
    <FieldD>7A02</FieldD>
    <FieldE>Yatala Brewery</FieldE>
    <FieldF>0</FieldF>
    <FieldG>16.2019</FieldG>
  </Details>
  <Details>
    <FieldA>275689</FieldA>
    <FieldC>EA</FieldC>
    <FieldD>7A02</FieldD>
    <FieldE>Yatala Brewery</FieldE>
    <FieldF>0</FieldF>
    <FieldG>17.2019</FieldG>
  </Details>
  <Details>
    <FieldA>275689</FieldA>
    <FieldC>EA</FieldC>
    <FieldD>7A02</FieldD>
    <FieldE>Yatala Brewery</FieldE>
    <FieldF>0</FieldF>
    <FieldG>18.2019</FieldG>
  </Details>
  <Details>
    <FieldA>275689</FieldA>
    <FieldC>EA</FieldC>
    <FieldD>7A02</FieldD>
    <FieldE>Yatala Brewery</FieldE>
    <FieldF>0</FieldF>
    <FieldG>19.2019</FieldG>
  </Details>
  <Details>
    <FieldA>275718</FieldA>
    <FieldC>EA</FieldC>
    <FieldD>7A01</FieldD>
    <FieldE>Abbotsford Brewery</FieldE>
    <FieldF>0</FieldF>
    <FieldG>06.2019</FieldG>
  </Details>
  <Details>
    <FieldA>275718</FieldA>
    <FieldC>EA</FieldC>
    <FieldD>7A01</FieldD>
    <FieldE>Abbotsford Brewery</FieldE>
    <FieldF>2016</FieldF>
    <FieldG>07.2019</FieldG>
  </Details>
  <Details>
    <FieldA>275718</FieldA>
    <FieldC>EA</FieldC>
    <FieldD>7A01</FieldD>
    <FieldE>Abbotsford Brewery</FieldE>
    <FieldF>0</FieldF>
    <FieldG>08.2019</FieldG>
  </Details>
  <Details>
    <FieldA>275718</FieldA>
    <FieldC>EA</FieldC>
    <FieldD>7A01</FieldD>
    <FieldE>Abbotsford Brewery</FieldE>
    <FieldF>0</FieldF>
    <FieldG>09.2019</FieldG>
  </Details>
  <Details>
    <FieldA>275718</FieldA>
    <FieldC>EA</FieldC>
    <FieldD>7A01</FieldD>
    <FieldE>Abbotsford Brewery</FieldE>
    <FieldF>0</FieldF>
    <FieldG>10.2019</FieldG>
  </Details>
  <Details>
    <FieldA>275718</FieldA>
    <FieldC>EA</FieldC>
    <FieldD>7A01</FieldD>
    <FieldE>Abbotsford Brewery</FieldE>
    <FieldF>0</FieldF>
    <FieldG>11.2019</FieldG>
  </Details>
  <Details>
    <FieldA>275718</FieldA>
    <FieldC>EA</FieldC>
    <FieldD>7A01</FieldD>
    <FieldE>Abbotsford Brewery</FieldE>
    <FieldF>0</FieldF>
    <FieldG>12.2019</FieldG>
  </Details>
  <Details>
    <FieldA>275718</FieldA>
    <FieldC>EA</FieldC>
    <FieldD>7A01</FieldD>
    <FieldE>Abbotsford Brewery</FieldE>
    <FieldF>0</FieldF>
    <FieldG>13.2019</FieldG>
  </Details>
  <Details>
    <FieldA>275718</FieldA>
    <FieldC>EA</FieldC>
    <FieldD>7A01</FieldD>
    <FieldE>Abbotsford Brewery</FieldE>
    <FieldF>0</FieldF>
    <FieldG>14.2019</FieldG>
  </Details>
  <Details>
    <FieldA>275718</FieldA>
    <FieldC>EA</FieldC>
    <FieldD>7A01</FieldD>
    <FieldE>Abbotsford Brewery</FieldE>
    <FieldF>0</FieldF>
    <FieldG>15.2019</FieldG>
  </Details>
  <Details>
    <FieldA>275718</FieldA>
    <FieldC>EA</FieldC>
    <FieldD>7A01</FieldD>
    <FieldE>Abbotsford Brewery</FieldE>
    <FieldF>0</FieldF>
    <FieldG>16.2019</FieldG>
  </Details>
  <Details>
    <FieldA>275718</FieldA>
    <FieldC>EA</FieldC>
    <FieldD>7A01</FieldD>
    <FieldE>Abbotsford Brewery</FieldE>
    <FieldF>0</FieldF>
    <FieldG>17.2019</FieldG>
  </Details>
  <Details>
    <FieldA>275718</FieldA>
    <FieldC>EA</FieldC>
    <FieldD>7A01</FieldD>
    <FieldE>Abbotsford Brewery</FieldE>
    <FieldF>0</FieldF>
    <FieldG>18.2019</FieldG>
  </Details>
  <Details>
    <FieldA>275718</FieldA>
    <FieldC>EA</FieldC>
    <FieldD>7A01</FieldD>
    <FieldE>Abbotsford Brewery</FieldE>
    <FieldF>0</FieldF>
    <FieldG>19.2019</FieldG>
  </Details>
  <Details>
    <FieldA>275718</FieldA>
    <FieldC>EA</FieldC>
    <FieldD>7A02</FieldD>
    <FieldE>Yatala Brewery</FieldE>
    <FieldF>0</FieldF>
    <FieldG>06.2019</FieldG>
  </Details>
  <Details>
    <FieldA>275718</FieldA>
    <FieldC>EA</FieldC>
    <FieldD>7A02</FieldD>
    <FieldE>Yatala Brewery</FieldE>
    <FieldF>0</FieldF>
    <FieldG>07.2019</FieldG>
  </Details>
  <Details>
    <FieldA>275718</FieldA>
    <FieldC>EA</FieldC>
    <FieldD>7A02</FieldD>
    <FieldE>Yatala Brewery</FieldE>
    <FieldF>4032</FieldF>
    <FieldG>08.2019</FieldG>
  </Details>
  <Details>
    <FieldA>275718</FieldA>
    <FieldC>EA</FieldC>
    <FieldD>7A02</FieldD>
    <FieldE>Yatala Brewery</FieldE>
    <FieldF>0</FieldF>
    <FieldG>09.2019</FieldG>
  </Details>
  <Details>
    <FieldA>275718</FieldA>
    <FieldC>EA</FieldC>
    <FieldD>7A02</FieldD>
    <FieldE>Yatala Brewery</FieldE>
    <FieldF>0</FieldF>
    <FieldG>10.2019</FieldG>
  </Details>
  <Details>
    <FieldA>275718</FieldA>
    <FieldC>EA</FieldC>
    <FieldD>7A02</FieldD>
    <FieldE>Yatala Brewery</FieldE>
    <FieldF>0</FieldF>
    <FieldG>11.2019</FieldG>
  </Details>
  <Details>
    <FieldA>275718</FieldA>
    <FieldC>EA</FieldC>
    <FieldD>7A02</FieldD>
    <FieldE>Yatala Brewery</FieldE>
    <FieldF>0</FieldF>
    <FieldG>12.2019</FieldG>
  </Details>
  <Details>
    <FieldA>275718</FieldA>
    <FieldC>EA</FieldC>
    <FieldD>7A02</FieldD>
    <FieldE>Yatala Brewery</FieldE>
    <FieldF>0</FieldF>
    <FieldG>13.2019</FieldG>
  </Details>
  <Details>
    <FieldA>275718</FieldA>
    <FieldC>EA</FieldC>
    <FieldD>7A02</FieldD>
    <FieldE>Yatala Brewery</FieldE>
    <FieldF>0</FieldF>
    <FieldG>14.2019</FieldG>
  </Details>
  <Details>
    <FieldA>275718</FieldA>
    <FieldC>EA</FieldC>
    <FieldD>7A02</FieldD>
    <FieldE>Yatala Brewery</FieldE>
    <FieldF>0</FieldF>
    <FieldG>15.2019</FieldG>
  </Details>
  <Details>
    <FieldA>275718</FieldA>
    <FieldC>EA</FieldC>
    <FieldD>7A02</FieldD>
    <FieldE>Yatala Brewery</FieldE>
    <FieldF>0</FieldF>
    <FieldG>16.2019</FieldG>
  </Details>
  <Details>
    <FieldA>275718</FieldA>
    <FieldC>EA</FieldC>
    <FieldD>7A02</FieldD>
    <FieldE>Yatala Brewery</FieldE>
    <FieldF>0</FieldF>
    <FieldG>17.2019</FieldG>
  </Details>
  <Details>
    <FieldA>275718</FieldA>
    <FieldC>EA</FieldC>
    <FieldD>7A02</FieldD>
    <FieldE>Yatala Brewery</FieldE>
    <FieldF>0</FieldF>
    <FieldG>18.2019</FieldG>
  </Details>
  <Details>
    <FieldA>275718</FieldA>
    <FieldC>EA</FieldC>
    <FieldD>7A02</FieldD>
    <FieldE>Yatala Brewery</FieldE>
    <FieldF>0</FieldF>
    <FieldG>19.2019</FieldG>
  </Details>
</CUBForeCast_New>